Workbook

Sheet 7210
A1: Kertas Kerja Analisis Beban Kerja (ABK) berdasarkan RO dan Rincian Pekerjaan | F1: - versi: 11 Juli 2026 - | G1: update: perbaikan aktivitas
A2: Unit Organisasi | B2: : BPS Kabupaten Sigi
A3: Kegiatan Tahun | B3: :
K5: Pemadanan Jabatan | M5: khusus JF
A6: Kode Unor (diisi untuk RO yang dikerjakan) | B6: Kondisi I = RO + Aktv. Awal II = RO Awal + Aktv. Baru III = RO Baru | C6: Bidang | D6: RO | E6: Aktivitas | F6: Rincian Pekerjaan | G6: Output Rincian Pekerjaan | H6: Waktu Penyelesaian Rincian Pekerjaan | I6: Volume Rincian Pekerjaan | J6: Satuan Output | K6: Jenis Jabatan (JPT/JA/JF/ Pelaksana) | L6: Jabatan (Nama Jabatan Lengkap) | M6: Jenjang (khusus JF) | N6: Unsur-Sub Unsur (Khusus JF) | O6: Padanan Butir JF | P6: Hasil Kerja | Q6: Angka Kredit (Akb) | R6: Konstanta (Kt) | S6: Waktu Penyelesaian Butir Kegiatan JF (Wpk) Akb/Kt | T6: Volume Kegiatan (V) | U6: Waktu Efektif Penyelesaian Volume Pekerjaan | V6: Hari | W6: Kebutuhan Pegawai JF | X6: Kebutuhan Pegawai (RP)
A7: - | B7: I | C7: Produksi | D7: Publikasi/Laporan Sensus Pertanian | E7: Analisis Hasil ST2023 | F7: Tidak ada | S7: =IFERROR(Q7/R7,"-") -> - | T7: ='Kertas Kerja'!$I268 | U7: =IFERROR(S7*T7,) | V7: =+U7/5.5 -> 0 | W7: =U7/1250 -> 0
A8: - | B8: I | C8: Produksi | D8: Publikasi/Laporan Sensus Pertanian | E8: Publisitas Hasil ST2023 | F8: Mempelajari pedoman dan materi publisitas ST2023 | G8: Pemahaman materi dan pedoman publisitas | H8: 5.5 | I8: 1 | J8: Kegiatan | S8: =IFERROR(Q8/R8,"-") -> - | T8: ='Kertas Kerja'!$I285 | U8: =IFERROR(S8*T8,) | V8: =+U8/5.5 -> 0 | W8: =U8/1250 -> 0
F9: Menyusun rencana pelaksanaan kegiatan publisitas | G9: Rencana pelaksanaan kegiatan | H9: 5.5 | I9: 1 | J9: dokumen
F10: Berkoordinasi dengan pemerintah daerah dan instansi terkait | G10: Hasil koordinasi/Notulen | H10: 5.5 | I10: 1 | J10: Kegiatan
F11: Menyiapkan bahan dan media publisitas | G11: Paket bahan publisitas (banner, leaflet, infografis, presentasi, dll.) | H11: 11 | I11: 1 | J11: Paket
F12: Menyusun Kerangka Acuan Kerja (KAK) kegiatan | G12: Dokumen KAK | H12: 5.5 | I12: 1 | J12: dokumen
F13: Menyusun pengajuan anggaran melalui BOS | G13: Dokumen pengajuan anggaran | H13: 5.5 | I13: 1 | J13: dokumen
F14: Membuat Surat Tugas pelaksanaan | G14: Surat Tugas | H14: 5.5 | I14: 1 | J14: dokumen
F15: Melaksanakan kegiatan sosialisasi/publisitas hasil ST2023 | G15: Kegiatan publisitas yang terlaksana | H15: 11 | I15: 1 | J15: Kegiatan
F16: Melakukan dokumentasi kegiatan | G16: Dokumentasi kegiatan | H16: 5.5 | I16: 1 | J16: Paket
F17: Menyusun laporan pelaksanaan publisitas | G17: Laporan kegiatan publisitas | H17: 5.5 | I17: 1 | J17: laporan
F18: Menyiapkan administrasi pertanggungjawaban kegiatan | G18: SPJ lengkap | H18: 11 | I18: 1 | J18: Paket
A19: - | B19: I | C19: Produksi | D19: Publikasi/Laporan Sensus Pertanian | E19: Survei Ekonomi Pertanian | F19: Mengikuti pelatihan Instruktur Daerah (INDA) | G19: Pelatihan selesai diikuti | H19: 11 | I19: 1 | J19: Sertifikat/daftar hadir
F20: Mengecek jumlah sampel | G20: Sampel | H20: 0.5 | I20: 1 | J20: dokumen
F21: Menyusun alokasi petugas lapangan | G21: Petugas teralokasi | H21: 0.5 | I21: 1 | J21: dokumen
F22: Menawarkan pekerjaan di Simitra | G22: Pekerjaan diterima oleh calon petugas | H22: 1 | I22: 1 | J22: kegiatan
F23: Membuat SK petugas | G23: SK yang telah ditandatangani pimpinan | H23: 1 | I23: 1 | J23: dokumen
F24: Menyiapkan administrasi pelatihan | G24: Berkas administrasi pelatihan | H24: 5.5 | I24: 1 | J24: dokumen
F25: Melatih petugas pendataan | G25: Pelatihan selesai diikuti | H25: 11 | I25: 1 | J25: dokumen
F26: Mengassign petugas ke aplikasi FASIH | G26: Petugas terassign | H26: 1 | I26: 1 | J26: kegiatan
F27: Menyiapkan instrumen pendataan | G27: Instrumen pendataan lengkap | H27: 5 | I27: 1 | J27: paket
F28: Menyusun KAK kegiatan | G28: KAK | H28: 1 | I28: 1 | J28: dokumen
F29: Membuat pengajuan anggaran di BOS untuk honor pendataan | G29: Pengajuan anggaran | H29: 1 | I29: 1 | J29: dokumen
F30: Membuat Surat Tugas pendataan | G30: Surat Tugas | H30: 1 | I30: 1 | J30: dokumen
F31: Menyusun KAK translok pengawasan | G31: KAK | H31: 1 | I31: 1 | J31: dokumen
... F39: Menyiapkan administrasi pencairan honor pengajar | G39: administrasi pencairan lengkap | H39: 11 | I39: 1 | J39: dokumen
A40: - | B40: I | C40: Produksi | D40: Publikasi/Laporan Sensus Pertanian | E40: Diseminasi | F40: Tidak ada | S40: =IFERROR(Q40/R40,"-") -> - | T40: ='Kertas Kerja'!$I269 | U40: =IFERROR(S40*T40,) | V40: =+U40/5.5 -> 0 | W40: =U40/1250 -> 0
A41: - | B41: I | C41: Produksi | D41: Publikasi/Laporan Sensus Pertanian | E41: Dukungan Penyelenggaraan Tugas dan Fungsi Unit | F41: Tidak ada | S41: =IFERROR(Q41/R41,"-") -> - | T41: ='Kertas Kerja'!$I270 | U41: =IFERROR(S41*T41,) | V41: =+U41/5.5 -> 0 | W41: =U41/1250 -> 0
A42: - | B42: I | C42: Produksi | D42: Publikasi/Laporan Statistik Sumber Daya Hayati | E42: Survei Perusahaan Kehutanan | F42: Tidak Ada
A43: - | B43: I | C43: Produksi | D43: Publikasi/Laporan Statistik Sumber Daya Hayati | E43: Survei Perusahaan Perikanan, TPI/PPI/PP | F43: Tidak Ada
A44: - | B44: I | C44: Produksi | D44: Publikasi/Laporan Statistik Industri | E44: IBS Bulanan | F44: Tidak Ada dialihkan ke triwulanan | S44: =IFERROR(Q44/R44,"-") -> - | T44: ='Kertas Kerja'!$I271 | U44: =IFERROR(S44*T44,) | V44: =+U44/5.5 -> 0 | W44: =U44/1250 -> 0
A45: - | B45: I | C45: Produksi | D45: Publikasi/Laporan Statistik Industri | E45: IBS Tahunan | F45: Mempelajari pedoman pelaksanaan Survei IBS Tahunan | G45: Pemahaman pedoman dan konsep survei | H45: 5.5 | I45: 1 | J45: Kegiatan | S45: =IFERROR(Q45/R45,"-") -> - | T45: ='Kertas Kerja'!$I272 | U45: =IFERROR(S45*T45,) | V45: =+U45/5.5 -> 0 | W45: =U45/1250 -> 0
F46: Mengecek jumlah perusahaan sampel | G46: Rekapitulasi jumlah perusahaan sampel yang telah diverifikasi | H46: 5.5 | I46: 1 | J46: Dokumen
F47: Memutakhirkan direktori perusahaan sampel | G47: Direktori perusahaan yang telah diperbarui | H47: 11 | I47: 1 | J47: Dokumen
F48: Menyusun alokasi petugas lapangan | G48: Dokumen alokasi petugas lapangan | H48: 5.5 | I48: 1 | J48: Dokumen
F49: Menawarkan pekerjaan di Simitra | G49: Petugas menerima penawaran pekerjaan | H49: 5.5 | I49: 1 | J49: Aplikasi
F50: Membuat SK petugas | G50: SK petugas yang telah ditandatangani | H50: 5.5 | I50: 1 | J50: Dokumen
F51: Menyiapkan administrasi pelatihan petugas | G51: Administrasi pelatihan lengkap | H51: 5.5 | I51: 1 | J51: Dokumen
F52: Melatih petugas pendataan | G52: Petugas yang telah mengikuti pelatihan | H52: 11 | I52: 1 | J52: Kegiatan
F53: Meng-assign petugas ke aplikasi pendataan | G53: Petugas ter-assign pada aplikasi | H53: 5.5 | I53: 1 | J53: Aplikasi
F54: Menyiapkan instrumen pendataan | G54: Instrumen pendataan siap digunakan | H54: 5.5 | I54: 1 | J54: Dokumen
F55: Menyusun Kerangka Acuan Kerja (KAK) pendataan | G55: Dokumen KAK pendataan | H55: 5.5 | I55: 1 | J55: Dokumen
F56: Membuat pengajuan anggaran di BOS untuk honor pendataan | G56: Dokumen pengajuan anggaran honor pendataan | H56: 5.5 | I56: 1 | J56: Dokumen
F57: Membuat Surat Tugas pendataan | G57: Surat Tugas pendataan | H57: 5.5 | I57: 1 | J57: Dokumen
... F65: Menyiapkan administrasi pencairan honor petugas (BAST dan dokumentasi) | G65: Berkas administrasi pencairan honor lengkap (BAST, daftar pembayaran, dokumentasi, dan dokumen pendukung) | H65: 11 | I65: 1 | J65: Paket
A66: - | B66: I | C66: Produksi | D66: Publikasi/Laporan Statistik Industri | E66: IBS Triwulanan | F66: Mengecek jumlah sampel | G66: Rekapitulasi jumlah sampel yang telah diverifikasi | H66: 5.5 | I66: 4 | J66: Dokumen | S66: =IFERROR(Q66/R66,"-") -> - | T66: ='Kertas Kerja'!$I273 | U66: =IFERROR(S66*T66,) | V66: =+U66/5.5 -> 0 | W66: =U66/1250 -> 0
F67: Memutakhirkan direktori usaha sampel (jika diperlukan) | G67: Direktori usaha yang telah diperbarui | H67: 11 | I67: 4 | J67: Dokumen
F68: Menyusun alokasi petugas lapangan | G68: Dokumen alokasi petugas lapangan | H68: 5.5 | I68: 2 | J68: Dokumen
F69: Menawarkan pekerjaan di Simitra (jika diperlukan) | G69: Petugas menerima penawaran pekerjaan | H69: 5.5 | I69: 2 | J69: Aplikasi
F70: Membuat SK petugas | G70: SK petugas yang telah ditandatangani | H70: 5.5 | I70: 2 | J70: Dokumen
F71: Menyiapkan administrasi pelatihan petugas | G71: Administrasi pelatihan lengkap | H71: 5.5 | I71: 2 | J71: Dokumen
F72: Melatih petugas pendataan | G72: Petugas yang telah mengikuti pelatihan | H72: 11 | I72: 2 | J72: Kegiatan
F73: Meng-assign petugas ke aplikasi pendataan | G73: Petugas ter-assign pada aplikasi | H73: 5.5 | I73: 2 | J73: Aplikasi
F74: Menyiapkan instrumen pendataan | G74: Instrumen pendataan siap digunakan | H74: 5.5 | I74: 2 | J74: Dokumen
F75: Menyusun KAK kegiatan pendataan | G75: Dokumen KAK pendataan | H75: 5.5 | I75: 2 | J75: Dokumen
F76: Membuat pengajuan anggaran di BOS untuk honor pendataan | G76: Dokumen pengajuan anggaran honor pendataan | H76: 5.5 | I76: 2 | J76: Dokumen
F77: Membuat Surat Tugas pendataan | G77: Surat Tugas pendataan | H77: 5.5 | I77: 2 | J77: Dokumen
F78: Menyusun KAK perjalanan/translok petugas | G78: Dokumen KAK perjalanan/translok | H78: 5.5 | I78: 2 | J78: Dokumen
... F85: Menyiapkan administrasi pencairan honor petugas (BAST dan dokumentasi) | G85: Berkas administrasi pencairan honor lengkap (BAST, daftar pembayaran, dokumentasi, dan dokumen pendukung) | H85: 11 | I85: 1 | J85: Paket
A86: - | B86: I | C86: Produksi | D86: Publikasi/Laporan Statistik Industri | E86: IMK Tahunan | F86: Mempelajari pedoman pelaksanaan Survei IMK Tahunan | G86: Pemahaman pedoman dan konsep survei | H86: 5.5 | I86: 4 | J86: Kegiatan | S86: =IFERROR(Q86/R86,"-") -> - | T86: ='Kertas Kerja'!$I274 | U86: =IFERROR(S86*T86,) | V86: =+U86/5.5 -> 0 | W86: =U86/1250 -> 0
F87: Mengecek jumlah usaha/perusahaan sampel | G87: Rekapitulasi jumlah sampel yang telah diverifikasi | H87: 5.5 | I87: 86 | J87: Dokumen
F88: Memutakhirkan direktori usaha sampel (jika diperlukan) | G88: Direktori usaha yang telah diperbarui | H88: 11 | I88: 2 | J88: Dokumen
F89: Menyusun alokasi petugas lapangan | G89: Dokumen alokasi petugas lapangan | H89: 5.5 | I89: 8 | J89: Dokumen
F90: Menawarkan pekerjaan di Simitra (jika diperlukan) | G90: Petugas menerima penawaran pekerjaan | H90: 5.5 | I90: 8 | J90: Aplikasi
F91: Membuat SK petugas | G91: SK petugas yang telah ditandatangani | H91: 5.5 | I91: 1 | J91: Dokumen
F92: Menyiapkan administrasi pelatihan petugas | G92: Administrasi pelatihan lengkap | H92: 5.5 | I92: 1 | J92: Dokumen
F93: Melatih petugas pendataan | G93: Petugas yang telah mengikuti pelatihan | H93: 11 | I93: 1 | J93: Kegiatan
F94: Meng-assign petugas ke aplikasi pendataan | G94: Petugas ter-assign pada aplikasi | H94: 5.5 | I94: 8 | J94: Aplikasi
F95: Menyiapkan instrumen pendataan | G95: Instrumen pendataan siap digunakan | H95: 5.5 | I95: 2 | J95: Dokumen
F96: Menyusun KAK kegiatan pendataan | G96: Dokumen KAK pendataan | H96: 5.5 | I96: 2 | J96: Dokumen
F97: Membuat pengajuan anggaran di BOS untuk honor pendataan | G97: Dokumen pengajuan anggaran honor pendataan | H97: 5.5 | I97: 1 | J97: Dokumen
F98: Membuat Surat Tugas pendataan | G98: Surat Tugas pendataan | H98: 5.5 | I98: 1 | J98: Dokumen
... F106: Menyiapkan administrasi pencairan honor petugas (BAST dan dokumentasi) | G106: Berkas administrasi pencairan honor lengkap (BAST, daftar pembayaran, dokumentasi, dan dokumen pendukung) | H106: 11 | I106: 3 | J106: Paket
A107: - | B107: I | C107: Produksi | D107: Publikasi/Laporan Statistik Industri | E107: IMK Triwulanan | F107: Mengecek jumlah sampel | G107: Rekapitulasi jumlah sampel yang telah diverifikasi | H107: 5.5 | I107: 46 | J107: Dokumen | S107: =IFERROR(Q107/R107,"-") -> - | T107: ='Kertas Kerja'!$I275 | U107: =IFERROR(S107*T107,) | V107: =+U107/5.5 -> 0 | W107: =U107/1250 -> 0
F108: Memutakhirkan direktori usaha sampel (jika diperlukan) | G108: Direktori usaha yang telah diperbarui | H108: 11 | I108: 46 | J108: Dokumen
F109: Menyusun alokasi petugas lapangan | G109: Dokumen alokasi petugas lapangan | H109: 5.5 | I109: 6 | J109: Dokumen
F110: Menawarkan pekerjaan di Simitra (jika diperlukan) | G110: Petugas menerima penawaran pekerjaan | H110: 5.5 | I110: 6 | J110: Aplikasi
F111: Membuat SK petugas | G111: SK petugas yang telah ditandatangani | H111: 5.5 | I111: 6 | J111: Dokumen
F112: Menyiapkan administrasi pelatihan petugas | G112: Administrasi pelatihan lengkap | H112: 5.5 | I112: 1 | J112: Dokumen
F113: Melatih petugas pendataan | G113: Petugas yang telah mengikuti pelatihan | H113: 11 | I113: 1 | J113: Kegiatan
F114: Meng-assign petugas ke aplikasi pendataan | G114: Petugas ter-assign pada aplikasi | H114: 5.5 | I114: 6 | J114: Aplikasi
F115: Menyiapkan instrumen pendataan | G115: Instrumen pendataan siap digunakan | H115: 5.5 | I115: 1 | J115: Dokumen
F116: Menyusun KAK kegiatan pendataan | G116: Dokumen KAK pendataan | H116: 5.5 | I116: 2 | J116: Dokumen
F117: Membuat pengajuan anggaran di BOS untuk honor pendataan | G117: Dokumen pengajuan anggaran honor pendataan | H117: 5.5 | I117: 1 | J117: Dokumen
F118: Membuat Surat Tugas pendataan | G118: Surat Tugas pendataan | H118: 5.5 | I118: 1 | J118: Dokumen
F119: Menyusun KAK perjalanan/translok petugas | G119: Dokumen KAK perjalanan/translok | H119: 5.5 | I119: 1 | J119: Dokumen
... F126: Menyiapkan administrasi pencairan honor petugas (BAST dan dokumentasi) | G126: Berkas administrasi pencairan honor lengkap (BAST, daftar pembayaran, dokumentasi, dan dokumen pendukung) | H126: 11 | I126: 2 | J126: Paket
A127: - | B127: I | C127: Produksi | D127: Publikasi/Laporan Statistik Sumber Daya Hayati | E127: Implementasi Pengumpulan Data Komoditas Pertanian Strategis Melalui Rumah Tangga | F127: Tidak ada | S127: =IFERROR(Q127/R127,"-") -> - | T127: ='Kertas Kerja'!$I276 | U127: =IFERROR(S127*T127,) | V127: =+U127/5.5 -> 0 | W127: =U127/1250 -> 0
A128: - | B128: I | C128: Produksi | D128: Publikasi/Laporan Statistik Sumber Daya Hayati | E128: Indepth Pendataan Statistik Tanaman Bawang dengan Metode Kerangka Sampling Area (KSA) | F128: Tidak ada | S128: =IFERROR(Q128/R128,"-") -> - | T128: ='Kertas Kerja'!$I277 | U128: =IFERROR(S128*T128,) | V128: =+U128/5.5 -> 0 | W128: =U128/1250 -> 0
A129: - | B129: I | C129: Produksi | D129: Publikasi/Laporan Sensus Pertanian | E129: Pengolahan Survei Ekonomi Pertanian | F129: tidak ada | S129: =IFERROR(Q129/R129,"-") -> - | T129: ='Kertas Kerja'!$I279 | U129: =IFERROR(S129*T129,) | V129: =+U129/5.5 -> 0 | W129: =U129/1250 -> 0
A130: - | B130: I | C130: Produksi | D130: Penyediaan dan Pembinaan Data 5 Sasaran Visi IE dan 45 IUP Statistik Industri | E130: Penyediaan dan Pembinaan Data 5 Sasaran Visi IE dan 45 IUP Statistik Industri | F130: tidak ada | S130: =IFERROR(Q130/R130,"-") -> - | T130: ='Kertas Kerja'!$I280 | U130: =IFERROR(S130*T130,) | V130: =+U130/5.5 -> 0 | W130: =U130/1250 -> 0
A131: - | B131: I | C131: Produksi | D131: Penyediaan dan Pembinaan Data 5 Sasaran Visi IE dan 45 IUP Statistik Sumber Daya Hayati | E131: Penyediaan dan Pembinaan Data 5 Sasaran Visi IE dan 45 IUP Statistik Sumber Daya Hayati | F131: tidak ada | S131: =IFERROR(Q131/R131,"-") -> - | T131: ='Kertas Kerja'!$I281 | U131: =IFERROR(S131*T131,) | V131: =+U131/5.5 -> 0 | W131: =U131/1250 -> 0
A132: - | B132: I | C132: Produksi | D132: Penyediaan dan Pembinaan Data 5 Sasaran Visi IE dan 45 IUP Statistik Sumber Daya Hayati | E132: Penyediaan dan Pembinaan Data 5 Sasaran Visi IE dan 45 IUP Statistik Sumber Daya Hayati | F132: tidak ada | S132: =IFERROR(Q132/R132,"-") -> - | T132: ='Kertas Kerja'!$I282 | U132: =IFERROR(S132*T132,) | V132: =+U132/5.5 -> 0 | W132: =U132/1250 -> 0
A133: - | B133: I | C133: Produksi | D133: Publikasi/Laporan Sensus Pertanian | E133: Penyusunan Sistem Informasi Geospasial Hasil ST2023 | F133: tidak ada | S133: =IFERROR(Q133/R133,"-") -> - | T133: ='Kertas Kerja'!$I283 | U133: =IFERROR(S133*T133,) | V133: =+U133/5.5 -> 0 | W133: =U133/1250 -> 0
A134: - | B134: I | C134: Produksi | D134: Publikasi/Laporan Sensus Pertanian | E134: Probity Audit ST2023 | F134: tidak ada | S134: =IFERROR(Q134/R134,"-") -> - | T134: ='Kertas Kerja'!$I284 | U134: =IFERROR(S134*T134,) | V134: =+U134/5.5 -> 0 | W134: =U134/1250 -> 0
...

Sheet Kertas Kerja
A1: Kertas Kerja Analisis Beban Kerja (ABK) berdasarkan RO dan Rincian Pekerjaan | F1: - versi: 11 Juli 2026 - | G1: update: perbaikan aktivitas
A2: Unit Organisasi | B2: :
A3: Kegiatan Tahun | B3: :
K5: Pemadanan Jabatan | M5: khusus JF
A6: Kode Unor (diisi untuk RO yang dikerjakan) | B6: Kondisi I = RO + Aktv. Awal II = RO Awal + Aktv. Baru III = RO Baru | C6: Bidang | D6: RO | E6: Aktivitas | F6: Rincian Pekerjaan | G6: Output Rincian Pekerjaan | H6: Waktu Penyelesaian Rincian Pekerjaan | I6: Volume Rincian Pekerjaan | J6: Satuan Output | K6: Jenis Jabatan (JPT/JA/JF/ Pelaksana) | L6: Jabatan (Nama Jabatan Lengkap) | M6: Jenjang (khusus JF) | N6: Unsur-Sub Unsur (Khusus JF) | O6: Padanan Butir JF | P6: Hasil Kerja | Q6: Angka Kredit (Akb) | R6: Konstanta (Kt) | S6: Waktu Penyelesaian Butir Kegiatan JF (Wpk) Akb/Kt | T6: Volume Kegiatan (V) | U6: Waktu Efektif Penyelesaian Volume Pekerjaan | V6: Hari | W6: Kebutuhan Pegawai JF | X6: Kebutuhan Pegawai (RP)
A7: - | B7: I | C7: Distribusi-Jasa | D7: Publikasi/Laporan Sensus Ekonomi | E7: Analisis Kegiatan Ekonomi dan Tematik Hasil SE2026 | L7: - | S7: =IFERROR(Q7/R7,"-") -> - | T7: ='Kertas Kerja'!$I268 | U7: =IFERROR(S7*T7,) | V7: =+U7/5.5 -> 0 | W7: =U7/1250 -> 0
A8: - | B8: I | C8: Distribusi-Jasa | D8: Publikasi/Laporan Sensus Ekonomi | E8: Dukungan Penyelenggaraan Tugas dan Fungsi Unit | S8: =IFERROR(Q8/R8,"-") -> - | T8: ='Kertas Kerja'!$I245 | U8: =IFERROR(S8*T8,) | V8: =+U8/5.5 -> 0 | W8: =U8/1250 -> 0
A9: - | B9: I | C9: Distribusi-Jasa | D9: Publikasi/Laporan Sensus Ekonomi | E9: Gladi Bersih SE2026 | S9: =IFERROR(Q9/R9,"-") -> - | T9: ='Kertas Kerja'!$I246 | U9: =IFERROR(S9*T9,) | V9: =+U9/5.5 -> 0 | W9: =U9/1250 -> 0
A10: - | B10: I | C10: Distribusi-Jasa | D10: Publikasi/Laporan Statistik Harga | E10: Indeks Kemahalan Konstruksi | S10: =IFERROR(Q10/R10,"-") -> - | T10: ='Kertas Kerja'!$I285 | U10: =IFERROR(S10*T10,) | V10: =+U10/5.5 -> 0 | W10: =U10/1250 -> 0
A11: - | B11: I | C11: Distribusi-Jasa | D11: Publikasi/Laporan Sensus Ekonomi | E11: Kajian Pembentukan Frame dan Wilayah Kerja Statistik SE2026 | S11: =IFERROR(Q11/R11,"-") -> - | T11: ='Kertas Kerja'!$I247 | U11: =IFERROR(S11*T11,) | V11: =+U11/5.5 -> 0 | W11: =U11/1250 -> 0
A12: - | B12: I | C12: Distribusi-Jasa | D12: Publikasi/Laporan Statistik Distribusi | E12: Kompilasi Data Statistik Ekspor | S12: =IFERROR(Q12/R12,"-") -> - | T12: ='Kertas Kerja'!$I269 | U12: =IFERROR(S12*T12,) | V12: =+U12/5.5 -> 0 | W12: =U12/1250 -> 0
A13: - | B13: I | C13: Distribusi-Jasa | D13: Publikasi/Laporan Statistik Distribusi | E13: Kompilasi Data Statistik Impor | S13: =IFERROR(Q13/R13,"-") -> - | T13: ='Kertas Kerja'!$I270 | U13: =IFERROR(S13*T13,) | V13: =+U13/5.5 -> 0 | W13: =U13/1250 -> 0
A14: - | B14: I | C14: Distribusi-Jasa | D14: Publikasi/Laporan Statistik Distribusi | E14: Kompilasi Data Statistik Jasa Transportasi | S14: =IFERROR(Q14/R14,"-") -> - | T14: ='Kertas Kerja'!$I271 | U14: =IFERROR(S14*T14,) | V14: =+U14/5.5 -> 0 | W14: =U14/1250 -> 0
A15: - | B15: I | C15: Distribusi-Jasa | D15: Publikasi/Laporan Statistik Distribusi | E15: Kompilasi Data Statistik Perdagangan Luar Negeri | S15: =IFERROR(Q15/R15,"-") -> - | T15: ='Kertas Kerja'!$I272 | U15: =IFERROR(S15*T15,) | V15: =+U15/5.5 -> 0 | W15: =U15/1250 -> 0
A16: - | B16: I | C16: Distribusi-Jasa | D16: Publikasi/Laporan Statistik Distribusi | E16: Kompilasi Data Transportasi | S16: =IFERROR(Q16/R16,"-") -> - | T16: ='Kertas Kerja'!$I273 | U16: =IFERROR(S16*T16,) | V16: =+U16/5.5 -> 0 | W16: =U16/1250 -> 0
A17: - | B17: I | C17: Distribusi-Jasa | D17: Publikasi/Laporan Statistik Jasa | E17: Passenger Exit Survey | S17: =IFERROR(Q17/R17,"-") -> - | T17: ='Kertas Kerja'!$I297 | U17: =IFERROR(S17*T17,) | V17: =+U17/5.5 -> 0 | W17: =U17/1250 -> 0
A18: - | B18: I | C18: Distribusi-Jasa | D18: Publikasi/Laporan Sensus Ekonomi | E18: Pelaksanaan SE2026 | S18: =IFERROR(Q18/R18,"-") -> - | T18: ='Kertas Kerja'!$I248 | U18: =IFERROR(S18*T18,) | V18: =+U18/5.5 -> 0 | W18: =U18/1250 -> 0
A19: - | B19: I | C19: Distribusi-Jasa | D19: Publikasi/Laporan Sensus Ekonomi | E19: Pelatihan Intama dan Innas | S19: =IFERROR(Q19/R19,"-") -> - | T19: ='Kertas Kerja'!$I249 | U19: =IFERROR(S19*T19,) | V19: =+U19/5.5 -> 0 | W19: =U19/1250 -> 0
A20: - | B20: I | C20: Distribusi-Jasa | D20: Publikasi/Laporan Sensus Ekonomi | E20: Pemutakhiran Kerangka Geospasial dan Muatan Wilkerstat | S20: =IFERROR(Q20/R20,"-") -> - | T20: ='Kertas Kerja'!$I250 | U20: =IFERROR(S20*T20,) | V20: =+U20/5.5 -> 0 | W20: =U20/1250 -> 0
A21: - | B21: I | C21: Distribusi-Jasa | D21: Publikasi/Laporan Statistik Distribusi | E21: Pendataan Ekspor Diluar Dokumen Bea Cukai | S21: =IFERROR(Q21/R21,"-") -> - | T21: ='Kertas Kerja'!$I274 | U21: =IFERROR(S21*T21,) | V21: =+U21/5.5 -> 0 | W21: =U21/1250 -> 0
A22: - | B22: I | C22: Distribusi-Jasa | D22: Publikasi/Laporan Sensus Ekonomi | E22: Penerapan Kerangka Geospasial dan Muatan Wilkerstat | S22: =IFERROR(Q22/R22,"-") -> - | T22: ='Kertas Kerja'!$I251 | U22: =IFERROR(S22*T22,) | V22: =+U22/5.5 -> 0 | W22: =U22/1250 -> 0
A23: - | B23: I | C23: Distribusi-Jasa | D23: Publikasi/Laporan Sensus Ekonomi | E23: Penerapan Prelist SBR Untuk SE2026 | S23: =IFERROR(Q23/R23,"-") -> - | T23: ='Kertas Kerja'!$I252 | U23: =IFERROR(S23*T23,) | V23: =+U23/5.5 -> 0 | W23: =U23/1250 -> 0
A24: - | B24: I | C24: Distribusi-Jasa | D24: Publikasi/Laporan Sensus Ekonomi | E24: Pengadaan Instrumen | S24: =IFERROR(Q24/R24,"-") -> - | T24: ='Kertas Kerja'!$I253 | U24: =IFERROR(S24*T24,) | V24: =+U24/5.5 -> 0 | W24: =U24/1250 -> 0
A25: - | B25: I | C25: Distribusi-Jasa | D25: Pengembangan Infrastruktur dan Layanan Teknologi Informasi dan Komunikasi | E25: Pengadaan TIK | S25: =IFERROR(Q25/R25,"-") -> - | T25: ='Kertas Kerja'!$I240 | U25: =IFERROR(S25*T25,) | V25: =+U25/5.5 -> 0 | W25: =U25/1250 -> 0
A26: - | B26: I | C26: Distribusi-Jasa | D26: Publikasi/Laporan Sensus Ekonomi | E26: Pengawasan Internal SE2026 | S26: =IFERROR(Q26/R26,"-") -> - | T26: ='Kertas Kerja'!$I254 | U26: =IFERROR(S26*T26,) | V26: =+U26/5.5 -> 0 | W26: =U26/1250 -> 0
A27: - | B27: I | C27: Distribusi-Jasa | D27: Publikasi/Laporan Sensus Ekonomi | E27: Pengolahan SE2026 | S27: =IFERROR(Q27/R27,"-") -> - | T27: ='Kertas Kerja'!$I255 | U27: =IFERROR(S27*T27,) | V27: =+U27/5.5 -> 0 | W27: =U27/1250 -> 0
A28: - | B28: I | C28: Distribusi-Jasa | D28: Publikasi/Laporan Statistik Distribusi | E28: Peningkatan Kualitas Pengisian Dokumen Pemberitahuan Ekspor Barang (PEB) | S28: =IFERROR(Q28/R28,"-") -> - | T28: ='Kertas Kerja'!$I275 | U28: =IFERROR(S28*T28,) | V28: =+U28/5.5 -> 0 | W28: =U28/1250 -> 0
A29: - | B29: I | C29: Distribusi-Jasa | D29: Penyediaan dan Pembinaan Data 5 Sasaran Visi IE dan 45 IUP Statistik Distribusi | E29: Penyediaan dan Pembinaan Data 5 Sasaran Visi IE dan 45 IUP Statistik Distribusi | S29: =IFERROR(Q29/R29,"-") -> - | T29: =#REF! -> #REF! | U29: =IFERROR(S29*T29,) | V29: =+U29/5.5 -> 0 | W29: =U29/1250 -> 0
A30: - | B30: I | C30: Distribusi-Jasa | D30: Penyediaan dan Pembinaan Data 5 Sasaran Visi IE dan 45 IUP Statistik Harga | E30: Penyediaan dan Pembinaan Data 5 Sasaran Visi IE dan 45 IUP Statistik Harga | S30: =IFERROR(Q30/R30,"-") -> - | T30: ='Kertas Kerja'!$I242 | U30: =IFERROR(S30*T30,) | V30: =+U30/5.5 -> 0 | W30: =U30/1250 -> 0
A31: - | B31: I | C31: Distribusi-Jasa | D31: Penyediaan dan Pembinaan Data 5 Sasaran Visi IE dan 45 IUP Statistik Jasa | E31: Penyediaan dan Pembinaan Data 5 Sasaran Visi IE dan 45 IUP Statistik Jasa | S31: =IFERROR(Q31/R31,"-") -> - | T31: =#REF! -> #REF! | U31: =IFERROR(S31*T31,) | V31: =+U31/5.5 -> 0 | W31: =U31/1250 -> 0
A32: - | B32: I | C32: Distribusi-Jasa | D32: Publikasi/Laporan Sensus Ekonomi | E32: Penyusunan Bahan Publisitas | S32: =IFERROR(Q32/R32,"-") -> - | T32: ='Kertas Kerja'!$I256 | U32: =IFERROR(S32*T32,) | V32: =+U32/5.5 -> 0 | W32: =U32/1250 -> 0
A33: - | B33: I | C33: Distribusi-Jasa | D33: Publikasi/Laporan Sensus Ekonomi | E33: Penyusunan Diseminasi SE2026 | S33: =IFERROR(Q33/R33,"-") -> - | T33: ='Kertas Kerja'!$I258 | U33: =IFERROR(S33*T33,) | V33: =+U33/5.5 -> 0 | W33: =U33/1250 -> 0
A34: - | B34: I | C34: Distribusi-Jasa | D34: Publikasi/Laporan Statistik Jasa | E34: Penyusunan Indeks Pembangunan Teknologi Informasi dan Komunikasi (ICT Development Index) | S34: =IFERROR(Q34/R34,"-") -> - | T34: ='Kertas Kerja'!$I298 | U34: =IFERROR(S34*T34,) | V34: =+U34/5.5 -> 0 | W34: =U34/1250 -> 0
A35: - | B35: I | C35: Distribusi-Jasa | D35: Publikasi/Laporan Statistik Jasa | E35: Penyusunan Inward FATS (Foreign Affiliate Statistics) | S35: =IFERROR(Q35/R35,"-") -> - | T35: =#REF! -> #REF! | U35: =IFERROR(S35*T35,) | V35: =+U35/5.5 -> 0 | W35: =U35/1250 -> 0
A36: - | B36: I | C36: Distribusi-Jasa | D36: Publikasi/Laporan Sensus Ekonomi | E36: Penyusunan Rancangan Analisis | S36: =IFERROR(Q36/R36,"-") -> - | T36: ='Kertas Kerja'!$I259 | U36: =IFERROR(S36*T36,) | V36: =+U36/5.5 -> 0 | W36: =U36/1250 -> 0
A37: - | B37: I | C37: Distribusi-Jasa | D37: Publikasi/Laporan Sensus Ekonomi | E37: Persiapan Diseminasi | S37: =IFERROR(Q37/R37,"-") -> - | T37: ='Kertas Kerja'!$I260 | U37: =IFERROR(S37*T37,) | V37: =+U37/5.5 -> 0 | W37: =U37/1250 -> 0
A38: - | B38: I | C38: Distribusi-Jasa | D38: Publikasi/Laporan Sensus Ekonomi | E38: Persiapan Publisitas Sensus Ekonomi (SE2026) | S38: =IFERROR(Q38/R38,"-") -> - | T38: ='Kertas Kerja'!$I261 | U38: =IFERROR(S38*T38,) | V38: =+U38/5.5 -> 0 | W38: =U38/1250 -> 0
A39: - | B39: I | C39: Distribusi-Jasa | D39: Publikasi/Laporan Sensus Ekonomi | E39: Post Enumeration Survey (PES) SE2026 | S39: =IFERROR(Q39/R39,"-") -> - | T39: ='Kertas Kerja'!$I262 | U39: =IFERROR(S39*T39,) | V39: =+U39/5.5 -> 0 | W39: =U39/1250 -> 0
A40: - | B40: I | C40: Distribusi-Jasa | D40: Publikasi/Laporan Sensus Ekonomi | E40: Probity Audit SE2026 | S40: =IFERROR(Q40/R40,"-") -> - | T40: ='Kertas Kerja'!$I263 | U40: =IFERROR(S40*T40,) | V40: =+U40/5.5 -> 0 | W40: =U40/1250 -> 0
A41: - | B41: I | C41: Distribusi-Jasa | D41: Publikasi/Laporan Sensus Ekonomi | E41: Publisitas SE2026 | S41: =IFERROR(Q41/R41,"-") -> - | T41: ='Kertas Kerja'!$I264 | U41: =IFERROR(S41*T41,) | V41: =+U41/5.5 -> 0 | W41: =U41/1250 -> 0
A42: - | B42: I | C42: Distribusi-Jasa | D42: Publikasi/Laporan Statistik Harga | E42: SPDT NTP | S42: =IFERROR(Q42/R42,"-") -> - | T42: ='Kertas Kerja'!$I286 | U42: =IFERROR(S42*T42,) | V42: =+U42/5.5 -> 0 | W42: =U42/1250 -> 0
A43: - | B43: I | C43: Distribusi-Jasa | D43: Publikasi/Laporan Statistik Jasa | E43: Statistik Lembaga Keuangan | S43: =IFERROR(Q43/R43,"-") -> - | T43: ='Kertas Kerja'!$I299 | U43: =IFERROR(S43*T43,) | V43: =+U43/5.5 -> 0 | W43: =U43/1250 -> 0
A44: - | B44: I | C44: Distribusi-Jasa | D44: Publikasi/Laporan Sensus Ekonomi | E44: Studi Cakupan Pelaku Usaha SE2026 | S44: =IFERROR(Q44/R44,"-") -> - | T44: ='Kertas Kerja'!$I265 | U44: =IFERROR(S44*T44,) | V44: =+U44/5.5 -> 0 | W44: =U44/1250 -> 0
A45: - | B45: I | C45: Distribusi-Jasa | D45: Publikasi/Laporan Statistik Distribusi | E45: Survei Angkutan Penumpang dan Barang di Terminal dan Jembatan Timbang | S45: =IFERROR(Q45/R45,"-") -> - | T45: ='Kertas Kerja'!$I276 | U45: =IFERROR(S45*T45,) | V45: =+U45/5.5 -> 0 | W45: =U45/1250 -> 0
A46: - | B46: I | C46: Distribusi-Jasa | D46: Publikasi/Laporan Statistik Harga | E46: Survei Biaya Hidup | S46: =IFERROR(Q46/R46,"-") -> - | T46: ='Kertas Kerja'!$I287 | U46: =IFERROR(S46*T46,) | V46: =+U46/5.5 -> 0 | W46: =U46/1250 -> 0
A47: - | B47: I | C47: Distribusi-Jasa | D47: Publikasi/Laporan Statistik Jasa | E47: Survei Bidang Jasa Pariwisata | S47: =IFERROR(Q47/R47,"-") -> - | T47: ='Kertas Kerja'!$I300 | U47: =IFERROR(S47*T47,) | V47: =+U47/5.5 -> 0 | W47: =U47/1250 -> 0
A48: - | B48: I | C48: Distribusi-Jasa | D48: Publikasi/Laporan Statistik E-Commerce | E48: Survei E-commerce | S48: =IFERROR(Q48/R48,"-") -> - | T48: ='Kertas Kerja'!$I284 | U48: =IFERROR(S48*T48,) | V48: =+U48/5.5 -> 0 | W48: =U48/1250 -> 0
A49: - | B49: I | C49: Distribusi-Jasa | D49: Publikasi/Laporan Penyusunan Inflasi | E49: Survei Harga Konsumen | S49: =IFERROR(Q49/R49,"-") -> - | T49: ='Kertas Kerja'!$I244 | U49: =IFERROR(S49*T49,) | V49: =+U49/5.5 -> 0 | W49: =U49/1250 -> 0
A50: - | B50: I | C50: Distribusi-Jasa | D50: Publikasi/Laporan Statistik Harga | E50: Survei Volume Penjualan Eceran Beras | S50: =IFERROR(Q50/R50,"-") -> - | T50: ='Kertas Kerja'!$I288 | U50: =IFERROR(S50*T50,) | V50: =+U50/5.5 -> 0 | W50: =U50/1250 -> 0
A51: - | B51: I | C51: Distribusi-Jasa | D51: Publikasi/Laporan Statistik Harga | E51: Survei Harga Perdagangan Besar | S51: =IFERROR(Q51/R51,"-") -> - | T51: ='Kertas Kerja'!$I289 | U51: =IFERROR(S51*T51,) | V51: =+U51/5.5 -> 0 | W51: =U51/1250 -> 0
A52: - | B52: I | C52: Distribusi-Jasa | D52: Publikasi/Laporan Statistik Harga | E52: Survei Harga Perdagangan Internasional | S52: =IFERROR(Q52/R52,"-") -> - | T52: ='Kertas Kerja'!$I290 | U52: =IFERROR(S52*T52,) | V52: =+U52/5.5 -> 0 | W52: =U52/1250 -> 0
A53: - | B53: I | C53: Distribusi-Jasa | D53: Publikasi/Laporan Statistik Harga | E53: Survei Harga Perdesaan | S53: =IFERROR(Q53/R53,"-") -> - | T53: ='Kertas Kerja'!$I291 | U53: =IFERROR(S53*T53,) | V53: =+U53/5.5 -> 0 | W53: =U53/1250 -> 0
A54: - | B54: I | C54: Distribusi-Jasa | D54: Publikasi/Laporan Statistik Harga | E54: Survei Harga Produsen | S54: =IFERROR(Q54/R54,"-") -> - | T54: ='Kertas Kerja'!$I292 | U54: =IFERROR(S54*T54,) | V54: =+U54/5.5 -> 0 | W54: =U54/1250 -> 0
A55: - | B55: I | C55: Distribusi-Jasa | D55: Publikasi/Laporan Statistik Harga | E55: Survei Harga Produsen Gabah | S55: =IFERROR(Q55/R55,"-") -> - | T55: ='Kertas Kerja'!$I293 | U55: =IFERROR(S55*T55,) | V55: =+U55/5.5 -> 0 | W55: =U55/1250 -> 0
A56: ppkk | B56: I | C56: Distribusi-Jasa | D56: Publikasi/Laporan Statistik Distribusi | E56: Survei Jasa Penunjang Angkutan (Pergudangan dan Kurir) | S56: =IFERROR(Q56/R56,"-") -> - | T56: ='Kertas Kerja'!$I283 | U56: =IFERROR(S56*T56,) | V56: =+U56/5.5 -> 0 | W56: =U56/1250 -> 0
A57: - | B57: I | C57: Distribusi-Jasa | D57: Publikasi/Laporan Statistik Harga | E57: Survei Kemahalan Konstruksi | S57: =IFERROR(Q57/R57,"-") -> - | T57: ='Kertas Kerja'!$I294 | U57: =IFERROR(S57*T57,) | V57: =+U57/5.5 -> 0 | W57: =U57/1250 -> 0
A58: - | B58: I | C58: Distribusi-Jasa | D58: Publikasi/Laporan Statistik Jasa | E58: Survei Outbound | S58: =IFERROR(Q58/R58,"-") -> - | T58: ='Kertas Kerja'!$I302 | U58: =IFERROR(S58*T58,) | V58: =+U58/5.5 -> 0 | W58: =U58/1250 -> 0
A59: - | B59: I | C59: Distribusi-Jasa | D59: Publikasi/Laporan Statistik Distribusi | E59: Survei Perdagangan Barang Domestik | S59: =IFERROR(Q59/R59,"-") -> - | T59: ='Kertas Kerja'!$I277 | U59: =IFERROR(S59*T59,) | V59: =+U59/5.5 -> 0 | W59: =U59/1250 -> 0
A60: - | B60: I | C60: Distribusi-Jasa | D60: Publikasi/Laporan Statistik Distribusi | E60: Survei Pola Barang Distribusi | S60: =IFERROR(Q60/R60,"-") -> - | T60: ='Kertas Kerja'!$I278 | U60: =IFERROR(S60*T60,) | V60: =+U60/5.5 -> 0 | W60: =U60/1250 -> 0
A61: - | B61: I | C61: Distribusi-Jasa | D61: Publikasi/Laporan Statistik Distribusi | E61: Survei Pola Usaha Non Pertanian | S61: =IFERROR(Q61/R61,"-") -> - | T61: ='Kertas Kerja'!$I279 | U61: =IFERROR(S61*T61,) | V61: =+U61/5.5 -> 0 | W61: =U61/1250 -> 0
A62: - | B62: I | C62: Distribusi-Jasa | D62: Publikasi/Laporan Statistik Distribusi | E62: Survei Profil Pasar, Pusat Perdagangan, dan Toko Modern | S62: =IFERROR(Q62/R62,"-") -> - | T62: ='Kertas Kerja'!$I280 | U62: =IFERROR(S62*T62,) | V62: =+U62/5.5 -> 0 | W62: =U62/1250 -> 0
A63: - | B63: I | C63: Distribusi-Jasa | D63: Publikasi/Laporan Statistik Jasa | E63: Survei Statistik Badan Usaha dan Pasar Modal | S63: =IFERROR(Q63/R63,"-") -> - | T63: ='Kertas Kerja'!$I303 | U63: =IFERROR(S63*T63,) | V63: =+U63/5.5 -> 0 | W63: =U63/1250 -> 0
A64: - | B64: I | C64: Distribusi-Jasa | D64: Publikasi/Laporan Statistik Harga | E64: Survei Statistik Harga Produsen | S64: =IFERROR(Q64/R64,"-") -> - | T64: ='Kertas Kerja'!$I296 -> 12 | U64: =IFERROR(S64*T64,) | V64: =+U64/5.5 -> 0 | W64: =U64/1250 -> 0
A65: - | B65: I | C65: Distribusi-Jasa | D65: Publikasi/Laporan Statistik Jasa | E65: Survei Statistik Keuangan Pemerintah Daerah | S65: =IFERROR(Q65/R65,"-") -> - | T65: ='Kertas Kerja'!$I304 | U65: =IFERROR(S65*T65,) | V65: =+U65/5.5 -> 0 | W65: =U65/1250 -> 0
A66: - | B66: I | C66: Distribusi-Jasa | D66: Publikasi/Laporan Statistik Distribusi | E66: Survei Triwulanan Kegiatan Usaha Terintegrasi | S66: =IFERROR(Q66/R66,"-") -> - | T66: ='Kertas Kerja'!$I281 | U66: =IFERROR(S66*T66,) | V66: =+U66/5.5 -> 0 | W66: =U66/1250 -> 0
A67: - | B67: I | C67: Distribusi-Jasa | D67: Publikasi/Laporan Statistik Distribusi | E67: Survei Waktu Tunggu (Dwelling Time) Di Pelabuhan | S67: =IFERROR(Q67/R67,"-") -> - | T67: ='Kertas Kerja'!$I282 | U67: =IFERROR(S67*T67,) | V67: =+U67/5.5 -> 0 | W67: =U67/1250 -> 0
A68: - | B68: I | C68: Distribusi-Jasa | D68: Publikasi/Laporan Statistik Jasa | E68: Survei Wisatawan Mancanegara | S68: =IFERROR(Q68/R68,"-") -> - | T68: ='Kertas Kerja'!$I305 | U68: =IFERROR(S68*T68,) | V68: =+U68/5.5 -> 0 | W68: =U68/1250 -> 0
A69: - | B69: I | C69: Distribusi-Jasa | D69: Publikasi/Laporan Sensus Ekonomi | E69: Uji Coba Pendataan SE2026-Lanjutan | S69: =IFERROR(Q69/R69,"-") -> - | T69: ='Kertas Kerja'!$I266 | U69: =IFERROR(S69*T69,) | V69: =+U69/5.5 -> 0 | W69: =U69/1250 -> 0
A70: - | B70: I | C70: Distribusi-Jasa | D70: Publikasi/Laporan Sensus Ekonomi | E70: Ujicoba SE2026 | S70: =IFERROR(Q70/R70,"-") -> - | T70: =#REF! -> #REF! | U70: =IFERROR(S70*T70,) | V70: =+U70/5.5 -> 0 | W70: =U70/1250 -> 0
A71: - | B71: I | C71: Distribusi-Jasa | D71: Publikasi/Laporan Sensus Ekonomi | E71: Updating Direktori Usaha/Perusahaan Ekonomi | S71: =IFERROR(Q71/R71,"-") -> - | T71: ='Kertas Kerja'!$I267 | U71: =IFERROR(S71*T71,) | V71: =+U71/5.5 -> 0 | W71: =U71/1250 -> 0
B72: I | C72: Dukman | D72: Layanan Reformasi Kinerja | E72: Briefing Pengelola SAKIP | S72: =IFERROR(Q72/R72,"-") -> - | T72: ='Kertas Kerja'!$I94 | U72: =IFERROR(S72*T72,) | V72: =+U72/5.5 -> 0 | W72: =U72/1250 -> 0
B73: I | C73: Dukman | D73: Layanan Reformasi Kinerja | E73: Capaian Kinerja Triwulanan | S73: =IFERROR(Q73/R73,"-") -> - | T73: ='Kertas Kerja'!$I103 | U73: =IFERROR(S73*T73,) | V73: =+U73/5.5 -> 0 | W73: =U73/1250 -> 0
A74: - | B74: I | C74: Dukman | D74: Layanan Manajemen Keuangan | E74: Entri RKAKL | S74: =IFERROR(Q74/R74,"-") -> - | T74: ='Kertas Kerja'!$I53 | U74: =IFERROR(S74*T74,) | V74: =+U74/5.5 -> 0 | W74: =U74/1250 -> 0
B75: I | C75: Dukman | D75: Layanan Reformasi Kinerja | E75: Evaluasi AKIP | S75: =IFERROR(Q75/R75,"-") -> - | T75: ='Kertas Kerja'!$I102 | U75: =IFERROR(S75*T75,) | V75: =+U75/5.5 -> 0 | W75: =U75/1250 -> 0
B76: I | C76: Dukman | D76: Layanan Perkantoran | E76: Kearsipan | S76: =IFERROR(Q76/R76,"-") -> - | T76: =#REF! -> #REF! | U76: =IFERROR(S76*T76,) | V76: =+U76/5.5 -> 0 | W76: =U76/1250 -> 0
B77: I | C77: Dukman | D77: Layanan Hubungan Masyarakat dan Informasi | E77: Kehumasan | S77: =IFERROR(Q77/R77,"-") -> - | T77: ='Kertas Kerja'!$I15 | U77: =IFERROR(S77*T77,) | V77: =+U77/5.5 -> 0 | W77: =U77/1250 -> 0
A78: - | B78: I | C78: Dukman | D78: Layanan Manajemen SDM | E78: Kepegawaian - Laporan LHKASN/SPT | S78: =IFERROR(Q78/R78,"-") -> - | T78: ='Kertas Kerja'!$I61 | U78: =IFERROR(S78*T78,) | V78: =+U78/5.5 -> 0 | W78: =U78/1250 -> 0
A79: - | B79: I | C79: Dukman | D79: Layanan Manajemen SDM | E79: Kepegawaian - Laporan LHKPN | S79: =IFERROR(Q79/R79,"-") -> - | T79: ='Kertas Kerja'!$I60 | U79: =IFERROR(S79*T79,) | V79: =+U79/5.5 -> 0 | W79: =U79/1250 -> 0
A80: - | B80: I | C80: Dukman | D80: Layanan Manajemen SDM | E80: Kepegawaian - Pemutakhiran Data Pegawai Bps | S80: =IFERROR(Q80/R80,"-") -> - | T80: ='Kertas Kerja'!$I59 | U80: =IFERROR(S80*T80,) | V80: =+U80/5.5 -> 0 | W80: =U80/1250 -> 0
A81: - | B81: I | C81: Dukman | D81: Layanan Manajemen SDM | E81: Kepegawaian - Pengelolaan Karis Karsu Pegawai | S81: =IFERROR(Q81/R81,"-") -> - | T81: ='Kertas Kerja'!$I70 | U81: =IFERROR(S81*T81,) | V81: =+U81/5.5 -> 0 | W81: =U81/1250 -> 0
A82: - | B82: I | C82: Dukman | D82: Layanan Manajemen SDM | E82: Kepegawaian - Pengelolaan SKP Pegawai | S82: =IFERROR(Q82/R82,"-") -> - | T82: ='Kertas Kerja'!$I69 | U82: =IFERROR(S82*T82,) | V82: =+U82/5.5 -> 0 | W82: =U82/1250 -> 0
A83: - | B83: I | C83: Dukman | D83: Layanan Manajemen SDM | E83: Kepegawaian - Pengelolaan Taspen | S83: =IFERROR(Q83/R83,"-") -> - | T83: ='Kertas Kerja'!$I71 | U83: =IFERROR(S83*T83,) | V83: =+U83/5.5 -> 0 | W83: =U83/1250 -> 0
A84: - | B84: I | C84: Dukman | D84: Layanan Manajemen SDM | E84: Kepegawaian - Pengembangan Kompetensi Pegawai | S84: =IFERROR(Q84/R84,"-") -> - | T84: ='Kertas Kerja'!$I74 | U84: =IFERROR(S84*T84,) | V84: =+U84/5.5 -> 0 | W84: =U84/1250 -> 0
A85: - | B85: I | C85: Dukman | D85: Layanan Manajemen SDM | E85: Kepegawaian - Pengurusan Kenaikan Gaji Berkala (KGB) | S85: =IFERROR(Q85/R85,"-") -> - | T85: ='Kertas Kerja'!$I72 | U85: =IFERROR(S85*T85,) | V85: =+U85/5.5 -> 0 | W85: =U85/1250 -> 0
A86: - | B86: I | C86: Dukman | D86: Layanan Manajemen SDM | E86: Kepegawaian - Pengurusan Lembur Pegawai | S86: =IFERROR(Q86/R86,"-") -> - | T86: ='Kertas Kerja'!$I67 | U86: =IFERROR(S86*T86,) | V86: =+U86/5.5 -> 0 | W86: =U86/1250 -> 0
A87: - | B87: I | C87: Dukman | D87: Layanan Manajemen SDM | E87: Kepegawaian - Pengurusan Tunjangan Kinerja | S87: =IFERROR(Q87/R87,"-") -> - | T87: ='Kertas Kerja'!$I66 | U87: =IFERROR(S87*T87,) | V87: =+U87/5.5 -> 0 | W87: =U87/1250 -> 0
A88: - | B88: I | C88: Dukman | D88: Layanan Manajemen SDM | E88: Kepegawaian - Pengurusan Uang Makan | S88: =IFERROR(Q88/R88,"-") -> - | T88: ='Kertas Kerja'!$I65 | U88: =IFERROR(S88*T88,) | V88: =+U88/5.5 -> 0 | W88: =U88/1250 -> 0
A89: - | B89: I | C89: Dukman | D89: Layanan Manajemen SDM | E89: Kepegawaian - Penyelenggaraan Apel dan Upacara | S89: =IFERROR(Q89/R89,"-") -> - | T89: ='Kertas Kerja'!$I64 | U89: =IFERROR(S89*T89,) | V89: =+U89/5.5 -> 0 | W89: =U89/1250 -> 0
A90: - | B90: I | C90: Dukman | D90: Layanan Manajemen SDM | E90: Kepegawaian - Penyelenggaraan Pemilihan Insan Statistik Teladan (IST) | S90: =IFERROR(Q90/R90,"-") -> - | T90: ='Kertas Kerja'!$I73 | U90: =IFERROR(S90*T90,) | V90: =+U90/5.5 -> 0 | W90: =U90/1250 -> 0
A91: - | B91: I | C91: Dukman | D91: Layanan Manajemen SDM | E91: Kepegawaian - Penyelenggaraan Ujian Dinas | S91: =IFERROR(Q91/R91,"-") -> - | T91: ='Kertas Kerja'!$I63 | U91: =IFERROR(S91*T91,) | V91: =+U91/5.5 -> 0 | W91: =U91/1250 -> 0
A92: - | B92: I | C92: Dukman | D92: Layanan Manajemen SDM | E92: Kepegawaian - Penyelenggaraan Ujian Penyesuiaian Ijazah | S92: =IFERROR(Q92/R92,"-") -> - | T92: ='Kertas Kerja'!$I62 | U92: =IFERROR(S92*T92,) | V92: =+U92/5.5 -> 0 | W92: =U92/1250 -> 0
A93: - | B93: I | C93: Dukman | D93: Layanan Manajemen SDM | E93: Kepegawaian - Rekap KJK Pegawai | S93: =IFERROR(Q93/R93,"-") -> - | T93: ='Kertas Kerja'!$I68 | U93: =IFERROR(S93*T93,) | V93: =+U93/5.5 -> 0 | W93: =U93/1250 -> 0
A94: - | B94: I | C94: Dukman | D94: Layanan Manajemen Keuangan | E94: Keuangan - Monitoring Realisasi KKP | S94: =IFERROR(Q94/R94,"-") -> - | T94: ='Kertas Kerja'!$I26 | U94: =IFERROR(S94*T94,) | V94: =+U94/5.5 -> 0 | W94: =U94/1250 -> 0
A95: - | B95: I | C95: Dukman | D95: Layanan Manajemen Keuangan | E95: Keuangan - Monitoring SPI Online | S95: =IFERROR(Q95/R95,"-") -> - | T95: ='Kertas Kerja'!$I44 | U95: =IFERROR(S95*T95,) | V95: =+U95/5.5 -> 0 | W95: =U95/1250 -> 0
A96: - | B96: I | C96: Dukman | D96: Layanan Manajemen Keuangan | E96: Keuangan - Pembayaran Dengan LS Bendahara | S96: =IFERROR(Q96/R96,"-") -> - | T96: ='Kertas Kerja'!$I39 | U96: =IFERROR(S96*T96,) | V96: =+U96/5.5 -> 0 | W96: =U96/1250 -> 0
A97: - | B97: I | C97: Dukman | D97: Layanan Manajemen Keuangan | E97: Keuangan - Pembayaran Dengan LS Pihak Ketiga (Kontraktual/Non Kontraktual) | S97: =IFERROR(Q97/R97,"-") -> - | T97: ='Kertas Kerja'!$I41 | U97: =IFERROR(S97*T97,) | V97: =+U97/5.5 -> 0 | W97: =U97/1250 -> 0
A98: - | B98: I | C98: Dukman | D98: Layanan Manajemen Keuangan | E98: Keuangan - Pembayaran Perjalanan Dinas Dengan UP/TUP | S98: =IFERROR(Q98/R98,"-") -> - | T98: ='Kertas Kerja'!$I38 | U98: =IFERROR(S98*T98,) | V98: =+U98/5.5 -> 0 | W98: =U98/1250 -> 0
A99: - | B99: I | C99: Dukman | D99: Layanan Manajemen Keuangan | E99: Keuangan - Pembayaran Tunai Pihak Ketiga | S99: =IFERROR(Q99/R99,"-") -> - | T99: ='Kertas Kerja'!$I42 | U99: =IFERROR(S99*T99,) | V99: =+U99/5.5 -> 0 | W99: =U99/1250 -> 0
A100: - | B100: I | C100: Dukman | D100: Layanan Manajemen Keuangan | E100: Keuangan - Pembayaran via CMS oleh Bendahara Pengeluaran | S100: =IFERROR(Q100/R100,"-") -> - | T100: ='Kertas Kerja'!$I40 | U100: =IFERROR(S100*T100,) | V100: =+U100/5.5 -> 0 | W100: =U100/1250 -> 0
A101: - | B101: I | C101: Dukman | D101: Layanan Manajemen Keuangan | E101: Keuangan - Penatausahaan Dokumen Keuangan | S101: =IFERROR(Q101/R101,"-") -> - | T101: ='Kertas Kerja'!$I45 | U101: =IFERROR(S101*T101,) | V101: =+U101/5.5 -> 0 | W101: =U101/1250 -> 0
...

Sheet Pembagian Tugas
A1: Arahan Sestama Pembagian Tugas Invetarisir Rincian Pekerjaan Riil Berdasarkan Bidang RO
O2: Jangan DIHAPUS!!!
A3: Unit Organisasi | B3: RO Bidang | O3: Jenis Jabatan | P3: Kondisi | Q3: Jabatan | R3: Jenjang
A4: BPS Provinsi Aceh | B4: Dukman | O4: Jabatan Pimpinan Tinggi | P4: I | Q4: Kepala | R4: Utama
A5: BPS Provinsi Sumatera Utara | B5: Dukman | O5: Jabatan Administrasi | P5: II | Q5: Wakil Kepala | R5: Madya
A6: BPS Provinsi Sumatera Barat | B6: Dukman | O6: Jabatan Fungsional | P6: III | Q6: Sekretaris Utama | R6: Muda
A7: BPS Provinsi Riau | B7: Dukman | O7: Jabatan Pelaksana | Q7: Deputi Bidang Metodologi dan Informasi Statistik | R7: Pertama
A8: BPS Provinsi Jambi | B8: Dukman | Q8: Deputi Bidang Statistik Sosial | R8: Penyelia
A9: BPS Provinsi Sumatera Selatan | B9: Dukman | Q9: Deputi Bidang Statistik Produksi | R9: Mahir
A10: BPS Provinsi Bengkulu | B10: MIS | Q10: Deputi Bidang Statistik Distribusi dan Jasa | R10: Terampil
A11: BPS Provinsi Lampung | B11: MIS | Q11: Deputi Bidang Neraca dan Analisis Statistik | R11: -
A12: BPS Provinsi Kepulauan Bangka Belitung | B12: MIS | Q12: Inspektur Utama
A13: BPS Provinsi Kepulauan Riau | B13: MIS | Q13: Kepala Pusat Pendidikan dan Pelatihan
A14: BPS Provinsi DKI Jakarta | B14: MIS | Q14: Kepala Biro Perencanaan dan Kerja Sama
A15: BPS Provinsi Jawa Barat | B15: Neraca | Q15: Kepala Biro Keuangan dan Barang Milik Negara
A16: BPS Provinsi Jawa Tengah | B16: Neraca | Q16: Kepala Biro Sumber Daya Manusia
A17: BPS Provinsi D I Yogyakarta | B17: Neraca | Q17: Kepala Biro Hukum dan Organisasi
A18: BPS Provinsi Jawa Timur | B18: Neraca | Q18: Kepala Biro Umum dan Hubungan Masyarakat
A19: BPS Provinsi Banten | B19: Neraca | Q19: Kepala Bagian Manajemen Risiko dan Dukungan Strategis Pimpinan
A20: BPS Provinsi Bali | B20: Distribusi-Jasa | Q20: Kepala Bagian Pengelolaan Barang Milik Negara
A21: BPS Provinsi Nusa Tenggara Barat | B21: Distribusi-Jasa | Q21: Kepala Bagian Rumah Tangga
A22: BPS Provinsi Nusa Tenggara Timur | B22: Distribusi-Jasa | Q22: Kepala Bagian Pengadaan Barang/Jasa
A23: BPS Provinsi Kalimantan Barat | B23: Distribusi-Jasa | Q23: Kepala Bagian Protokol dan Tata Usaha Pimpinan
... A37: BPS Provinsi Papua | B37: Sosial | Q37: Direktur Statistik Sumber Daya Hayati
Q38: Direktur Statistik Sumber Daya Mineral dan Konstruksi
Q39: Direktur Statistik Industri
Q40: Direktur Statistik Distribusi
Q41: Direktur Statistik Harga
Q42: Direktur Statistik Jasa
Q43: Direktur Neraca Produksi
Q44: Direktur Neraca Pengeluaran
Q45: Direktur Analisis Statistik dan Neraca Satelit
Q46: Inspektur I
Q47: Inspektur II
Q48: Inspektur III
Q49: Kepala Subdirektorat Sains Data
... Q106: -

Sheet Kamus Ruta
A1: Uraian Pekerjaan Lv 3 | B1: Uraian Pekerjaan Lv 4
A2: Menyusun KAK kegiatan
A3: Identifikasi Sampel Blok Sensus | B3: Menyiapkan kerangka sampel
B4: Finalisasi kerangka sampel
B5: Menarik sampel blok sensus
B6: Menganalisis sampel blok sensus
B7: Menarik sampel blok sensus pengganti
B8: Finalisasi blok sensus terpilih
B9: Menarik sampel rumah tangga oleh BPS Pusat
B10: Mengirim sampel rumah tangga ke BPS Daerah
B11: Menarik sampel rumah tangga oleh BPS Daerah
A12: Menyusun alokasi petugas lapangan | B12: Melihat Kebutuhan Petugas dan instruktur yang dibutuhkan
B13: Membandingkan kebutuhan jumlah dan kualifikasi petugas dengan ketersediaan jumlah dan kualifikasi petugas yang masih tersedia
B14: Menyiapkan mekanisme perekrutan petugas dan instruktur sesuai dengan kebutuhan yang belum terpenuhi
B15: Menginput biodata petugas dan instruktur baru untuk suvei berjalan dan untuk kebutuhan survei selanjutnya
B16: Membuat daftar alokasi petugas
B17: Menyusun draft dokumen kontrak untuk petugas mitra
B18: Membuat daftar calon instruktur berikut dengan alokasi tugas mengajar
A19: Melatih petugas pendataan | B19: Merencanakan waktu, tempat, dan biaya pelatihan
B20: Menyiapkan materi pelatihan dan berkas administrasi pelatihan
B21: Menyelenggarakan pelatihan
B22: Menentukan alokasi kerja instruktur
B23: Menetapkan dokumen kontrak petugas
B24: Menyusun laporan hasil pelatihan
A25: Menyiapkan sumber daya dan instrumen pengumpulan data | B25: Mencetak instrumen untuk pendataan PAPI
B26: Mendistribusikan instrumen pendataan ke BPS Daerah
B27: Memeriksa ketersediaan komponen IT pendukung pengumpulan data
B28: Melengkapi komponen TI pendukung yang belum tersedia
B29: Melakukan setting infrastruktur TI sesuai kebutuhan pendataan
A30: Menyiapkan instrumen untuk quality assurance/penjaminan kualitas | B30: Menyesuaikan sumber daya, instrumen dan prosedur Quality Assurance
B31: Cetak instrumen Quality Assurance
B32: Melakukan instalasi instrumen Quality Assurance ke perangkat CAPI
B33: Melakukan instalasi instrumen Quality Assurance ke production server CAWI
B34: Melatih Petugas Quality Assurance
B35: Mendistribusikan perangkat dan instrumen Quality Assurance
A37: Send Out pre-Collection Information/Sosialisasi Kegiatan Survei dan Sensus | B37: Menyiapkan informasi pra-survei untuk dikirim ke calon responden
B38: Mendesain informasi pra survei
B39: Mendistribusikan softcopy desain informasi pra-survei ke BPS daerah
B40: Mencetak informasi pra-survei
B41: Mendistribusikan informasi pra-survei kepada calon responden
A42: Updating/Listing
A43: Pengawasan/Pemeriksaan dokumen updating/listing
A44: Entri dokumen updating/listing
A45: Penarikan sampel survei
A46: Collect Data/Pengumpulan data | B46: Wawancara dan mengisi kuesioner (PAPI)
B47: Menyerahkan kuesioner ke pengawas (PAPI)
B48: Wawancara dan input kuesioner (CAPI)
B49: Menyiapkan token dan link entri mandiri (CAWI)
B50: Mengisi kuesioner online mandiri (CAWI)
B51: Wawancara, rekam, dan entri data (CATI)
B52: Mengawasi pendataan yg dilakukan oleh petugas pencacah
B53: Memeriksa status dan paradata kuesioner (CATI/CAWI/CAPI)
B54: Konfirmasi dan memperbaiki isian (CATI/CAWI/CAPI)
B55: Approve dokumen (CATI/CAWI/CAPI)
B56: Memeriksa rambu-rambu dan kewajaran kuesioner (PAPI)
B57: Mengembalikan dokumen ke pencacahan (PAPI)
B58: Konfirmasi dan memperbaiki isian (PAPI)
... B60: Mengirim dokumen ke BPS kabupaten (PAPI)
A61: Pengawasan/Pemeriksaan Data
A62: Supervisi lapangan oleh BPS daerah
A63: Receiving batching
A64: Monitor and report data collection progress/Monitoring progress pendataan | B64: Mengevaluasi kegiatan pengumpulan data
B65: Melakukan penilaian kualitas data
B66: Menyusun rekomendasi terkait kualitas data
B67: Mengevaluasi progres kegiatan pencacahan
B68: Menyusun rekomendasi aksi response rate
B69: Mengevaluasi kinerja petugas
B70: Menyusun rekomendasi solusi terhadap kinerja petugas
B71: Menyusun laporan progres pengumpulan data
A72: Non Responds Follow Up/Revisit Non Responds | B72: Mengkaji laporan progres pengumpulan data dan rekomendasinya
B73: Revisit ke responden yang menolak diwawancara
B74: Konfirmasi isian kepada petugas
B75: Revisit responden untuk konfirmasi isian
B76: Meminta responden menandatangani formulir menolak wawancara
B77: Memperbaiki/melengkapi isian sesuai keterangan petugas
B78: Collect/receive data
B79: Menyusun laporan tindak lanjut non-response
A80: Data entry/Perekaman Data | B80: Menyiapkan dokumen untuk dientri
B81: Entry data dan paradata (process metadata)
B82: Mengecek dan melaporkan progress entry data
B83: Submit data entri ke dalam database
A84: Mengarsipkan instrumen pencacahan | B84: Melakukan batching instrumen yang sudah dientri
B85: Mengkonfirmasi kekurangan dokumen kepada PJ pengolahan
B86: Menyimpan perangkat/dokumen pengumpulan data
B87: Menyusun dokumentasi pengarsipan dokumen
A88: Input data validation/Melakukan validasi data | B88: Cek kelengkapan script validasi
B89: Menjalankan validasi data
B90: Mereview hasil validasi data
B91: Finalisasi hasil validasi data
A92: Error report/Konfirmasi hasil validasi data ke petugas | B92: Mengidentifikasi saran penyelesaian eror
B93: Mengidentifikasi aktor yang terlibat
B94: Membuat laporan validasi
B95: Memeriksa laporan validasi
B96: Finalisasi laporan penyelesaian eror
B97: Memeriksa kelengkapan laporan eror
B98: Menyusun laporan penyelesaian eror
A99: Data Editing and imputation/Perbaikan isian dan imputasi data berdasarkan keadaan lapangan | B99: Cek kelengkapan script editing
B100: Melakukan editing
B101: Mereview hasil editing data
B102: Finalisasi hasil editing data
...

Sheet Kamus SPV
A1: Kegiatan | B1: Rincian Pekerjaan | C1: Output | D1: Satuan Output
A2: Supervisi | B2: Menyusun rencana supervisi | C2: Dokumen rencana supervisi | D2: Dokumen
A3: Supervisi | B3: Menelaah dokumen sebelum supervisi | C3: Dokumen hasil telaah | D3: Dokumen
A4: Supervisi | B4: Menyusun instrumen/checklist supervisi | C4: Instrumen supervisi | D4: Dokumen
A5: Supervisi | B5: Melaksanakan supervisi lapangan | C5: Kegiatan supervisi terlaksana | D5: Kegiatan
A6: Supervisi | B6: Melakukan observasi pelaksanaan kegiatan | C6: Hasil observasi | D6: Laporan/Catatan
A7: Supervisi | B7: Melakukan wawancara dengan pelaksana | C7: Berita acara/catatan wawancara | D7: Dokumen
A8: Supervisi | B8: Melakukan verifikasi kesesuaian pelaksanaan | C8: Hasil verifikasi | D8: Dokumen
A9: Supervisi | B9: Memberikan arahan atau pembinaan saat supervisi | C9: Sesi pembinaan | D9: Sesi
A10: Supervisi | B10: Menyusun rekomendasi hasil supervisi | C10: Dokumen rekomendasi | D10: Dokumen
A11: Supervisi | B11: Menyusun laporan hasil supervisi | C11: Laporan supervisi | D11: Laporan
A12: Supervisi | B12: Menyampaikan hasil supervisi kepada unit terkait | C12: Penyampaian hasil supervisi | D12: Kegiatan
A13: Supervisi | B13: Memantau tindak lanjut hasil supervisi | C13: Laporan pemantauan tindak lanjut | D13: Laporan

Sheet Kamus Usaha-Bisnis
A1: Uraian Pekerjaan Lv 3 | B1: Uraian Pekerjaan lv. 4
A2: Menyusun KAK kegiatan
B3: Mempersiapkan kerangka sampel
A4: Identifikasi Sampel | B4: Menyiapkan kerangka sample yang akan digunakan
B5: Memilih Sampel
B6: Menganalisis Daftar Sampel
B7: Memberikan pertimbangan terkait sampel terpilih
B8: Finalisasi daftar sampel terpilih
A9: Menyusun alokasi petugas lapangan | B9: Melihat jumlah dan kualifikasi petugas dan instruktur yang dibutuhkan
B10: Membandingkan kebutuhan dengan ketersediaan petugas dan infrastruktur
B11: Merekrut calon petugas dan instruktur sesuai kebutuhan
B12: Menginput data calon petugas dan instruktur
B13: Membuat daftar alokasi petugas
B14: Membuat draft dokumen kontrak
B15: Membuat daftar calon instruktur
A16: Melatih petugas pendataan | B16: Mengakses daftar calon peserta pelatihan
B17: Mengakses daftar calon instruktur pelatihan
B18: Merencanakan waktu, tempat, dan biaya pelatihan
B19: Menyiapkan materi pelatihan
B20: Menyiapkan dokumen administrasi pelatihan
B21: Menyelenggarakan pelatihan
B22: Menentukan alokasi kerja instruktur
B23: Menetapkan dokumen kontrak petugas
B24: Melaporkan hasil pelatihan
A25: Menyiapkan sumber daya dan instrumen pengumpulan data | B25: Mencetak instrumen pengumpulan data
B26: Memeriksa ketersediaan semua komopnen TI pendukung kegiatan pengumpulan data
B27: Menyiapkan komponen TI pendukung yang belum tersedia
B28: Setting infrastruktur TI sesuai dengan kebutuhan pengumpulan data
B29: Mendistribusikan instrumen kepada PO sesuai jadwal yang ditentukan
B30: Menerima sumber daya/instrumen pengumpulan data tingkat provinsi
B31: Mendistribusikan sumber daya/instrumen kepada DO sesuai jadwal yang ditentukan
B32: Menerima sumber daya/instrumen pengumpulan data tingkat kota/kab
B33: Mendistribusikan sumber daya/instrumen kepada petugas pengumpulan data
B34: Pengadaan perlengkapan kegiatan
A35: Menyiapkan instrumen untuk quality assurance/penjaminan kualitas | B35: Menyesuaikan sumber daya, instrumen dan prosedur QA (SMS)
B36: Cetak instrumen QA
B37: Instal instrumen QA ke perangkat CATI
B38: Instal instrumen QA ke production server CAWI
A39: Send Out pre-Collection Information/Sosialisasi Kegiatan Survei dan Sensus | B39: Mengakses informasi daftar sampel
B40: Loading daftar sampel ke aplikasi pengumpulan data
B41: Mengirimkan daftar sampel SMADO
B42: Mendistribusikan daftar sampel ke field force enumerator
B43: Menyiapkan pemberitahuan informasi pre-survei
B44: Mengirimkan informasi pre-survei ke responden
B45: Melakukan konfirmasi kesediaan responden
A46: Updating/Listing
A47: Pengawasan/Pemeriksaan dokumen updating/lsiting
A48: Entri dokumen updating/listing
A49: Penarikan sampel survei | B49: salam pembuka dan perjanjian wawancara
A50: Collect Data/Pengumpulan data | B50: Wawancara responden
A51: Pengawasan/Pemeriksaan Data | B51: Mengisi kuesioner paper
B52: Menyerahkan kuesioner kepada field supervisor
B53: Menerima kuesioner paper dari field enumerator
B54: input kuesioner CAPI
B55: Submit kuesioner CAPI
B57: Lapor kepada Field Supervisor
B58: Field supervisor melakukan perjanjian wawancara
B59: Lapor kepada distric/provincial office
B60: Distric/profincial office melakukan wawancara
B61: Menelpon
B62: melakukan wawancara kepada responden
B63: menginput dan merekam jawaban responden
B64: Submit isian hasil wawancara
... B69: Membuat surat pernyataan tidak bersedia diwawancara
A70: Supervisi lapangan oleh BPS daerah
A71: Receiving batching
A72: Monitor and report data collection progress/Monitoring progress pendataan | B72: Pengawasan pencacahan CAI
B73: Melakukan pengawasan pencacah lapangan
B74: Melaporkan kemajuan kegiatan pencacahanm sensus/survei
B75: Monitoring progress pencacahan CAI dan PAPI
B76: Menyusun laporan dan evaluasi
B77: Membuat preformance report
B78: Membuat rekomendasi aksi untuk petugas pencacahan
B79: Mengupdate data performa petugas pencacahan
B80: Membuat progress report
B81: Membuat rekomendasi aksi response rate rendah
B82: Membuat evaluation report
B83: Membuat rekomendasi terhadap kualitas data
A84: Non Responds Follow Up/Revisit Non Responds | B84: Melakukan evaluasi non-respond pada response rate rendah
B85: Menyusun rencana tidak lanjut non-respon response rate
B86: Melakukan evaluasi kualitas data
B87: Menyusun rencana tindak lanjut non-respon kualitas data
B88: Finalisasi tindak lanjut non-respon
B89: Melakukan rekomendasi non-respon
A90: Data entry/Perekaman Data | B90: Pengelompokan (batching) dokumen
B91: Editing dan Coding
B92: Entri Dokumen
B93: Cetak error report
B94: Menyusun resolusi error
B95: Penyimpanan dokumen fisik
B96: Pengiriman data hasil entri
A97: Mengarsipkan instrumen pencacahan | B97: Menyiapkan dan mengirim dokumen pengumpulan data
B98: Memeriksa kelengkapan dan batching dokumen pengumpulan data
B99: Melakukan konfirmasi kelengkapan dokumen pengumpulan data
B100: Membuat berita acara serah terima barang
B101: Menyimpan perangkat/dokumen pengumpulan data
A102: Input data validation/Melakukan validasi data | B102: Membaca record data
B103: membaca validation rule
B104: cek kelengkapan validasi
B105: Perbaikan atau penambahan validation rule
...

Sheet Kamus Usaha-Ruta
A1: Uraian Pekerjaan Lv 3 | B1: Uraian Pekerjaan Lv 4
A2: Menyusun KAK kegiatan
A3: Identifikasi Sampel Blok Sensus | B3: Menyiapkan kerangka sampel
B4: Finalisasi kerangka sampel
B5: Menarik sampel blok sensus
B6: Menganalisis sampel blok sensus
B7: Menarik sampel blok sensus pengganti
B8: Finalisasi blok sensus terpilih
B9: Menarik sampel rumah tangga oleh BPS Pusat
B10: Mengirim sampel rumah tangga ke BPS Daerah
B11: Menarik sampel rumah tangga oleh BPS Daerah
A12: Menyusun alokasi petugas lapangan | B12: Melihat Kebutuhan Petugas dan instruktur yang dibutuhkan
B13: Membandingkan kebutuhan jumlah dan kualifikasi petugas dengan ketersediaan jumlah dan kualifikasi petugas yang masih tersedia
B14: Menyiapkan mekanisme perekrutan petugas dan instruktur sesuai dengan kebutuhan yang belum terpenuhi
B15: Menginput biodata petugas dan instruktur baru untuk suvei berjalan dan untuk kebutuhan survei selanjutnya
B16: Membuat daftar alokasi petugas
B17: Menyusun draft dokumen kontrak untuk petugas mitra
B18: Membuat daftar calon instruktur berikut dengan alokasi tugas mengajar
A19: Melatih petugas pendataan | B19: Merencanakan waktu, tempat, dan biaya pelatihan
B20: Menyiapkan materi pelatihan dan berkas administrasi pelatihan
B21: Menyelenggarakan pelatihan
B22: Menentukan alokasi kerja instruktur
B23: Menetapkan dokumen kontrak petugas
B24: Menyusun laporan hasil pelatihan
A25: Menyiapkan sumber daya dan instrumen pengumpulan data | B25: Mencetak instrumen untuk pendataan PAPI
B26: Mendistribusikan instrumen pendataan ke BPS Daerah
B27: Memeriksa ketersediaan komponen IT pendukung pengumpulan data
B28: Melengkapi komponen TI pendukung yang belum tersedia
B29: Melakukan setting infrastruktur TI sesuai kebutuhan pendataan
A30: Menyiapkan instrumen untuk quality assurance/penjaminan kualitas | B30: Menyesuaikan sumber daya, instrumen dan prosedur Quality Assurance
B31: Cetak instrumen Quality Assurance
B32: Melakukan instalasi instrumen Quality Assurance ke perangkat CAPI
B33: Melakukan instalasi instrumen Quality Assurance ke production server CAWI
B34: Melatih Petugas Quality Assurance
B35: Mendistribusikan perangkat dan instrumen Quality Assurance
A36: Send Out pre-Collection Information/Sosialisasi Kegiatan Survei dan Sensus | B36: Menyiapkan informasi pra-survei untuk dikirim ke calon responden
B37: Mendesain informasi pra survei
B38: Mendistribusikan softcopy desain informasi pra-survei ke BPS daerah
B39: Mencetak informasi pra-survei
B40: Mendistribusikan informasi pra-survei kepada calon responden
A41: Updating/Listing
A42: Pengawasan/Pemeriksaan dokumen updating/listing
A43: Entri dokumen updating/listing
A44: Penarikan sampel survei
A45: Collect Data/Pengumpulan data | B45: Wawancara dan mengisi kuesioner (PAPI)
B46: Menyerahkan kuesioner ke pengawas (PAPI)
B47: Wawancara dan input kuesioner (CAPI)
B48: Menyiapkan token dan link entri mandiri (CAWI)
B49: Mengisi kuesioner online mandiri (CAWI)
B50: Wawancara, rekam, dan entri data (CATI)
B51: Mengawasi pendataan yg dilakukan oleh petugas pencacah
B52: Memeriksa status dan paradata kuesioner (CATI/CAWI/CAPI)
B53: Konfirmasi dan memperbaiki isian (CATI/CAWI/CAPI)
B54: Approve dokumen (CATI/CAWI/CAPI)
B55: Memeriksa rambu-rambu dan kewajaran kuesioner (PAPI)
B56: Mengembalikan dokumen ke pencacahan (PAPI)
B57: Konfirmasi dan memperbaiki isian (PAPI)
... B59: Mengirim dokumen ke BPS kabupaten (PAPI)
A60: Pengawasan/Pemeriksaan Data
A61: Supervisi lapangan oleh BPS daerah
A62: Receiving batching
A63: Monitor and report data collection progress/Monitoring progress pendataan | B63: Mengevaluasi kegiatan pengumpulan data
B64: Melakukan penilaian kualitas data
B65: Menyusun rekomendasi terkait kualitas data
B66: Mengevaluasi progres kegiatan pencacahan
B67: Menyusun rekomendasi aksi response rate
B68: Mengevaluasi kinerja petugas
B69: Menyusun rekomendasi solusi terhadap kinerja petugas
B70: Menyusun laporan progres pengumpulan data
A71: Non Responds Follow Up/Revisit Non Responds | B71: Mengkaji laporan progres pengumpulan data dan rekomendasinya
B72: Revisit ke responden yang menolak diwawancara
B73: Konfirmasi isian kepada petugas
B74: Revisit responden untuk konfirmasi isian
B75: Meminta responden menandatangani formulir menolak wawancara
B76: Memperbaiki/melengkapi isian sesuai keterangan petugas
B77: Collect/receive data
B78: Menyusun laporan tindak lanjut non-response
A79: Data entry/Perekaman Data | B79: Menyiapkan dokumen untuk dientri
B80: Entry data dan paradata (process metadata)
B81: Mengecek dan melaporkan progress entry data
B82: Submit data entri ke dalam database
A83: Mengarsipkan instrumen pencacahan | B83: Melakukan batching instrumen yang sudah dientri
B84: Mengkonfirmasi kekurangan dokumen kepada PJ pengolahan
B85: Menyimpan perangkat/dokumen pengumpulan data
B86: Menyusun dokumentasi pengarsipan dokumen
A87: Input data validation/Melakukan validasi data | B87: Cek kelengkapan script validasi
B88: Menjalankan validasi data
B89: Mereview hasil validasi data
B90: Finalisasi hasil validasi data
A91: Error report/Konfirmasi hasil validasi data ke petugas | B91: Mengidentifikasi saran penyelesaian eror
B92: Mengidentifikasi aktor yang terlibat
B93: Membuat laporan validasi
B94: Memeriksa laporan validasi
B95: Finalisasi laporan penyelesaian eror
B96: Memeriksa kelengkapan laporan eror
B97: Menyusun laporan penyelesaian eror
A98: Data Editing and imputation/Perbaikan isian dan imputasi data berdasarkan keadaan lapangan | B98: Cek kelengkapan script editing
B99: Melakukan editing
B100: Mereview hasil editing data
B101: Finalisasi hasil editing data
...

Sheet Kamus Harga
A1: Uraian Pekerjaan Lv 3 | B1: Uraian Pekerjaan lv. 4
A2: Menyusun KAK kegiatan
B3: Menyiapkan kerangka sampel
B4: Finalisasi kerangka sampel
A5: Identifikasi sampel | B5: Menarik sampel Tahap 1
B6: Menganalisis sampel tahap 1
B7: Menarik sampel tahap 1 pengganti
B8: Finalisasi sampel terpilih tahap 1
B9: Menarik sampel responden oleh BPS Pusat
B10: Mengirim sampel tahap 1 ke BPS daerah
B11: Menarik sampel responden oleh BPS Daerah
A12: Menyusun alokasi petugas lapangan | B12: Melihat kebutuhan petugas dan instruktur yang dibutuhkan
B13: Membandingkan kebutuhan jumlah dan kualifikasi petugas dengan ketersediaan jumlah dan kualifikasi petugas yang masih tersedia
B14: Menyiapkan mekanisme perekrutan petugas dan instruktur sesuai dengan kebutuhan yang belum memenuhi
B15: Menginput biodata petugas dan instruktur baru untuk survei berjalan dan untuk kebutuhan survei selanjutnya
B16: Membuat daftar alokasi petugas berdasarkan survei kontrol file
B17: Menyusun draft dokumen kontrak untuk petugas mitra
B18: Membuat daftar calon instruktur berikut dengan alokasi tugas mengajar
A19: Melatih petugas pendataan | B19: Merencanakan waktu, tempat dan biaya pelatihan
B20: Menyiapkan materi pelatihan dan berkas administrasi pelatihan
B21: Menyelenggarakan pelatihan
B22: Menentukan alokasi kerja instruktur
B23: Menetapkan dokumen kontrak petugas
B24: Menyusun laporan hasil pelatihan
A25: Menyiapkan sumber daya dan instrumen pengumpulan data | B25: Mencetak instrumen untuk pendataan PAPI
B26: Mendistribusikan instrumen pendataan ke BPS Daerah
B27: Memeriksa ketersediaan komponen IT pendukung pengumpulan data
B28: Melengkapi komponen TI pendukung yang belum tersedia
B29: Melakukan setting infrastruktur TI sesuai kebutuhan pendataan
A30: Menyiapkan instrumen untuk quality assurance/penjaminan kualitas | B30: Menyesuaikan sumber daya, instrumen dan prosedur QA
B31: Cetak instrumen QA
B32: Melakukan instalasi instrumen QA ke perangkat CAPI
B33: Melakukan instalasi instrumen QA ke production server
B34: Melatih petugas
B35: Mendistribusikan perangkat dan instrumen QA
A36: Send Out pre-Collection Information/Sosialisasi Kegiatan Survei dan Sensus | B36: Menyiapkan informasi pra-survei untuk dikirim ke calon responden
B37: Mendesain informasi pra-survei
B38: Mendistribusikan softcopy desain informasi pra-survei ke BPS Daerah
B39: Mencetak informasi pra-survei
B40: Mendistribusikan informasi pra-survei kepada calon responden
A41: Updating/Listing
A42: Pengawasan/Pemeriksaan dokumen updating/lsiting
A43: Entri dokumen updating/listing
A44: Penarikan sampel survei
A45: Collect Data/Pengumpulan data | B45: Wawancara dan mengisi kuesioner
A46: Pengawasan/Pemeriksaan Data | B46: Menyerahkan kuesioner ke pengawas
B47: Wawancara dan input kuesioner CAPI
B48: Menyiapkan token dan link entri mandiri
B49: Mengisi kuesioner online mandiri
B50: Wawancara, rekam dan entri data
B51: Mengawasi pendataan petugas yang menjadi tanggung jawabnya
B52: Memeriksa status dan paradata kuesioner
B53: Konfirmasi dan memperbaiki isian
B54: Approve dokumen
B55: Memeriksa rambu-rambu dan kewajaran kuesioner
B56: Mengembalikan dokumen ke pencacah
B57: Konfirmasi dan memperbaiki isian
B58: Melakukan pengkodean dokumen
... B62: Memeriksa rambu-rambu dan kewajaran kuesioner
A63: Supervisi lapangan oleh BPS daerah
A66: Receiving batching
A67: Monitor and report data collection progress/Monitoring progress pendataan | B67: Mengevaluasi kegiatan pengumpulan
B68: Melakukan penilaian kualitas data
B69: Menyusun rekomendasi terkait kualitas data
B70: Mengevaluasi progres kegiatan pendataan
B71: Menyusun rekomendasi aksi response rate
B72: Mengevaluasi kinerja petugas
B73: Menyusun rekomendasi solusi terhadap kinerja petugas
B74: Menyusun laporan progress pengumpulan
A75: Non Responds Follow Up/Revisit Non Responds | B75: Mengkaji laporan progres pengumpulan data dan rekomendasinya
B76: Revisit ke responden yang menolak diwawancara
B77: Konfirmasi isian kepada petugas
B78: Revisit responden untuk konfirmasi isian
B79: Meminta responden menandatangani formulir menolak wawancara
B80: Memperbaiki/melengkapi isian sesuai keterangan petugas
B81: Collect/receive data
B82: Menyusun laporan tindak lanjut non-response
A83: Data entry/Perekaman Data | B83: Menyiapkan dokumen untuk dientri
B84: Entry data dan paradata (process metadata)
B85: Mengecek dan melaporkan progress entry data
B86: Submit data entri ke dalam database
A87: Mengarsipkan instrumen pencacahan | B87: Melakukan batching instrumen yang sudah dientri
B88: Mengkonfirmasi kekurangan dokumen kepada PJ pengolahan
B89: Menyimpan perangkat/dokumen pengumpulan data
B90: Menyusun dokumentasi pengarsipan dokumen
A91: Input data validation/Melakukan validasi data | B91: Cek kelengkapan script validasi
B92: Menjalankan validasi data
B93: Mereview hasil validasi data
B94: Finalisasi hasil validasi data
A95: Error report/Konfirmasi hasil validasi data ke petugas | B95: Mengidentifikasi saran penyelesaian eror
B96: Mengidentifikasi aktor yang terlibat
B97: Membuat laporan validasi
B98: Memeriksa laporan validasi
B99: Finalisasi laporan penyelesaian eror
B100: Memeriksa kelengkapan laporan eror
B101: Menyusun laporan penyelesaian eror
A102: Data Editing and imputation/Perbaikan isian dan imputasi data berdasarkan keadaan lapangan | B102: Cek kelengkapan script editing
B103: Melakukan editing
B104: Mereview hasil editing data
B105: Finalisasi hasil editing data
...

Sheet Kamus Area
A1: Uraian Pekerjaan Lv 3
A2: Menyusun KAK kegiatan
A3: Memilih Alokasi Sampel
A4: Menyusun alokasi petugas lapangan
A5: Melatih petugas pendataan
A6: Menyiapkan sumber daya dan instrumen pengumpulan data
A7: Pengenalan Segmen Terpilih
A8: Melakukan pendataan dengan aplikasi CAPI
A9: Pengawasan/Pemeriksaan Data
A10: Supervisi lapangan oleh BPS daerah
A11: Mengirimkan hasil pengamatan melalui aplikasi
A12: Menggambar Peta Wilayah
... A16: Monitor and report data collection progress/Monitoring progress pendataan

Sheet Kamus Kompromin
A1: Uraian Pekerjaan Lv 3
A2: Penyiapan pengumpulan data
A3: Pelatihan petugas
A4: Pengumpulan data
A5: Pengawasan dan pemeriksaan data
A6: Supervisi pengumpulan data
A7: Coding, validasi, dan imputasi data
A8: Melakukan analisis deskriptif
A9: Publisitas/diseminasi hasil pendataan

Sheet Dukman Prov
A3: Kode Satker | B3: Nama Satker | C3: Kegiatan (After) | D3: Aktivitas | E3: Unit Eselon II | F3: Uraian Pekerjaan
C4: SAKIP | D4: Pembentukan Tim SAKIP | E4: 2100 Biro Perencanaan | F4: Membentuk Tim SAKIP
C5: SAKIP | D5: Pembentukan Tim SAKIP | E5: 2100 Biro Perencanaan | F5: Penyusunan SK Tim SAKIP
C6: SAKIP | D6: Briefing Pengelola SAKIP | E6: 2100 Biro Perencanaan | F6: Pembuatan Surat Undangan Briefing Pengelola SAKIP
C7: SAKIP | D7: Briefing Pengelola SAKIP | E7: 2100 Biro Perencanaan | F7: Pembuatan Daftar Hadir Briefing Pengelola SAKIP
C8: SAKIP | D8: Briefing Pengelola SAKIP | E8: 2100 Biro Perencanaan | F8: Penyusunan Notulen Briefing Pengelola SAKIP
C9: SAKIP | D9: Briefing Pengelola SAKIP | E9: 2100 Biro Perencanaan | F9: Penyusunan Dokumentasi Briefing Pengelola SAKIP
C10: SAKIP | D10: Briefing Pengelola SAKIP | E10: 2100 Biro Perencanaan | F10: Pembuatan Surat Undangan Narasumber Briefing Pengelola SAKIP
C11: SAKIP | D11: Pembinaan Tim SAKIP | E11: 2100 Biro Perencanaan | F11: Workshop Tim SAKIP oleh Inspektorat/Biro Perencanaan
C12: SAKIP | D12: Pembinaan Tim SAKIP | E12: 2100 Biro Perencanaan | F12: Penyusunan Surat Permohonan Narasumber Pembinaan Tim SAKIP BPS Provinsi dan BPS Kabupaten/Kota
C13: SAKIP | D13: Pembinaan Tim SAKIP | E13: 2100 Biro Perencanaan | F13: Koordinasi Permohonan Narasumber Pembinaan Tim SAKIP BPS Provinsi dan BPS Kabupaten/Kota
C14: SAKIP | D14: Pembinaan Tim SAKIP | E14: 2100 Biro Perencanaan | F14: Pembuatan Virtual Background/Backdrop Pembinaan Tim SAKIP BPS Provinsi dan BPS Kabupaten/Kota
C15: SAKIP | D15: Pembinaan Tim SAKIP | E15: 2100 Biro Perencanaan | F15: Penyusunan Surat Undangan dan Daftar Hadir Pembinaan Tim SAKIP BPS Provinsi dan BPS Kabupaten/Kota
... C582: Reformasi Kinerja | D582: EPSS | E582: 2100 Biro Perencanaan | F582: Memberikan approval terhadap surat rekomendasi hasil EPSS untuk TPB di wilayahnya

Sheet Dukman Kako
A3: Kode Satker | B3: Nama Satker | C3: Kegiatan | D3: Aktivitas | E3: Unit Eselon II | F3: Uraian Pekerjaan
C4: Perencanaan dan Penganggaran | D4: Penyusunan RKAKL | E4: 2100 Biro Perencanaan | F4: Penyusunan Pagu Indikatif
C5: =C4 -> Perencanaan dan Penganggaran | D5: Penyusunan RKAKL | E5: 2100 Biro Perencanaan | F5: Menerima surat dan rincian dasar hitung
C6: =C5 -> Perencanaan dan Penganggaran | D6: Penyusunan RKAKL | E6: 2100 Biro Perencanaan | F6: Melakukan input dalam aplikasi SAKTI-Dukman
C7: =C6 -> Perencanaan dan Penganggaran | D7: Penyusunan RKAKL | E7: 2100 Biro Perencanaan | F7: Melakukan input dalam aplikasi SAKTI-PPIS
C8: =C7 -> Perencanaan dan Penganggaran | D8: Penyusunan RKAKL | E8: 2100 Biro Perencanaan | F8: Melakukan input RPD dalam aplikasi SAKTI-Dukman
C9: =C8 -> Perencanaan dan Penganggaran | D9: Penyusunan RKAKL | E9: 2100 Biro Perencanaan | F9: Melakukan input RPD dalam aplikasi SAKTI-PPIS
C10: =C9 -> Perencanaan dan Penganggaran | D10: Penyusunan RKAKL | E10: 2100 Biro Perencanaan | F10: Melakukan Validasi
C11: =C10 -> Perencanaan dan Penganggaran | D11: Penyusunan RKAKL | E11: 2100 Biro Perencanaan | F11: Aproval dan submit unit
C12: =C11 -> Perencanaan dan Penganggaran | D12: Penyusunan RKAKL | E12: 2100 Biro Perencanaan | F12: Melakukan Pencetakan RKA
C13: =C12 -> Perencanaan dan Penganggaran | D13: Penyusunan RKAKL | E13: 2100 Biro Perencanaan | F13: Filling dokumen
C14: =C13 -> Perencanaan dan Penganggaran | D14: Penyusunan RKAKL | E14: 2100 Biro Perencanaan | F14: Dasar Hitung Petugas Y+1
C15: =C14 -> Perencanaan dan Penganggaran | D15: Penyusunan RKAKL | E15: 2100 Biro Perencanaan | F15: Penerimaan Surat permintaan jumlah petugas dari BPS Provinsi
C16: =C15 -> Perencanaan dan Penganggaran | D16: Penyusunan RKAKL | E16: 2100 Biro Perencanaan | F16: Kompilasi data jumlah petugas dari ketua tim di BPS Kab/Kota
... C119: =C118 -> Perencanaan dan Penganggaran | D119: SK Kegiatan | E119: 2100 Biro Perencanaan | F119: Filling Dokumen (Softfile & Hardfile)
C120: SAKIP | D120: Perjanjian Kinerja | E120: 2100 Biro Perencanaan | F120: Membentuk tim SAKIP
C121: SAKIP | D121: Perjanjian Kinerja | E121: 2100 Biro Perencanaan | F121: Membuat SK Tim
C122: SAKIP | D122: Perjanjian Kinerja | E122: 2100 Biro Perencanaan | F122: Penyusunan Laporan Kinerja
C123: SAKIP | D123: Perjanjian Kinerja | E123: 2100 Biro Perencanaan | F123: Menerima prototype LAKIP BPS dan memberikan arahan kepada anggota tim
C124: SAKIP | D124: Perjanjian Kinerja | E124: 2100 Biro Perencanaan | F124: Menerima konsep surat dari BPS provinsi
C125: SAKIP | D125: Perjanjian Kinerja | E125: 2100 Biro Perencanaan | F125: Menyiapkan dan mempelajari materi serta bahan pendukung penyusunan LAKIP
C126: SAKIP | D126: Perjanjian Kinerja | E126: 2100 Biro Perencanaan | F126: Mengolah data realisasi kegiatan dengan menggunakan formulir Pengukuran Kinerja
C127: SAKIP | D127: Perjanjian Kinerja | E127: 2100 Biro Perencanaan | F127: Menghitung nilai capaian kinerja dengan menggunakan rumus-rumus secara tepat
C128: SAKIP | D128: Perjanjian Kinerja | E128: 2100 Biro Perencanaan | F128: Mengolah data bahan masukan penyusunan narasi
C129: SAKIP | D129: Perjanjian Kinerja | E129: 2100 Biro Perencanaan | F129: Menyampaikan konsep hasil pengolahan LAKIP
C130: SAKIP | D130: Perjanjian Kinerja | E130: 2100 Biro Perencanaan | F130: Memeriksa konsep LAKIP BPS berdasarkan bahan pendukung
C131: SAKIP | D131: Perjanjian Kinerja | E131: 2100 Biro Perencanaan | F131: Pembahasan bersama LAKIP
... C588: BMN | D588: PBJ - Pengelolaan sanggah pada pekerjaan dengan metode pemilihan Tender/Seleksi/Penunjukan Langsung | E588: 2500 Biro Umum | F588: 4. Mengumumkan hasil dari penanganan sanggahan kepada pihak yang terlibat, termasuk peserta pengadaan yang mengajukan sanggahan.
C589: BMN | D589: PBJ - Pengelolaan sanggah pada pekerjaan dengan metode pemilihan Tender/Seleksi/Penunjukan Langsung | E589: 2500 Biro Umum
C590: BMN | D590: PBJ - Negosiasi dengan mengacu pada Harga Perkiraan Sendiri (HPS) dan standar harga/biaya | E590: 2500 Biro Umum | F590: 1. Mempelajari dan memahami HPS yang telah ditetapkan dan mengidentifikasi standar harga/biaya yang relevan untuk pekerjaan yang akan dilaksanakan;
C591: BMN | D591: PBJ - Negosiasi dengan mengacu pada Harga Perkiraan Sendiri (HPS) dan standar harga/biaya | E591: 2500 Biro Umum | F591: 2. Mengevaluasi penawaran awal dari penyedia untuk memastikan bahwa harga yang diajukan sesuai dengan HPS dan standar harga/biaya yang telah ditetapkan;
C592: BMN | D592: PBJ - Negosiasi dengan mengacu pada Harga Perkiraan Sendiri (HPS) dan standar harga/biaya | E592: 2500 Biro Umum | F592: 3. Klarifikasi dengan penyedia untuk menjelaskan HPS dan standar harga/biaya yang ditetapkan;
C593: BMN | D593: PBJ - Negosiasi dengan mengacu pada Harga Perkiraan Sendiri (HPS) dan standar harga/biaya | E593: 2500 Biro Umum | F593: 4. Melakukan negosiasi dengan penyedia terkait dengan harga yang ditetapkan
C594: BMN | D594: PBJ - Negosiasi dengan mengacu pada Harga Perkiraan Sendiri (HPS) dan standar harga/biaya | E594: 2500 Biro Umum | F594: 5. Membuat berita acara negosiasi harga dan dokumentasi
C595: BMN | D595: PBJ - Negosiasi pada pekerjaan dengan metode pemilihan Tender/Seleksi/Penunjukan Langsung | E595: 2500 Biro Umum | F595: 1. Mempelajari dan memahami HPS yang telah ditetapkan dan mengidentifikasi standar harga/biaya yang relevan untuk pekerjaan yang akan dilaksanakan;
C596: BMN | D596: PBJ - Negosiasi pada pekerjaan dengan metode pemilihan Tender/Seleksi/Penunjukan Langsung | E596: 2500 Biro Umum | F596: 2. Mengevaluasi penawaran awal dari penyedia untuk memastikan bahwa harga yang diajukan sesuai dengan HPS dan standar harga/biaya yang telah ditetapkan;
C597: BMN | D597: PBJ - Negosiasi pada pekerjaan dengan metode pemilihan Tender/Seleksi/Penunjukan Langsung | E597: 2500 Biro Umum | F597: 3. Klarifikasi dengan penyedia untuk menjelaskan HPS dan standar harga/biaya yang ditetapkan;
C598: BMN | D598: PBJ - Negosiasi pada pekerjaan dengan metode pemilihan Tender/Seleksi/Penunjukan Langsung | E598: 2500 Biro Umum | F598: 4. Melakukan negosiasi dengan penyedia terkait dengan harga yang ditetapkan;
C599: BMN | D599: PBJ - Negosiasi pada pekerjaan dengan metode pemilihan Tender/Seleksi/Penunjukan Langsung | E599: 2500 Biro Umum | F599: 5. Membuat berita acara negosiasi harga dan dokumentasi.
C600: BMN | D600: PBJ - Pendampingan /konsultasi penggunaan sistem informasi/aplikasi pada tahap pemilihan penyedia | E600: 2500 Biro Umum | F600: 1. Memberikan bimbingan dan penjelasan kepada pihak-pihak yang terlibat mengenai penggunaan sistem informasi atau aplikasi yang digunakan dalam proses pemilihan penyedia;
C601: BMN | D601: PBJ - Pendampingan /konsultasi penggunaan sistem informasi/aplikasi pada tahap pemilihan penyedia | E601: 2500 Biro Umum | F601: 2. Memantau dan memastikan bahwa penggunaan sistem informasi atau aplikasi dilakukan dengan benar dan sesuai dengan prosedur yang telah ditetapkan;
... C616: BMN | D616: PBJ - Evaluasi kinerja penyedia barang/jasa | E616: 2500 Biro Umum | F616: 4. Menggunakan hasil evaluasi penyedia sebagai tolak ukur kerja sama dengan penyedia tersebut di masa yang akan datang.

Sheet Kamus Uraian Pekerjaan
A1: Kode Satker | B1: Satker | C1: Kegiatan | D1: Aktivitas | E1: Unit Eselon II | F1: Uraian Pekerjaan
C2: Economy-Wide Survey | D2: Economy-Wide Survey | E2: 2100 Biro Perencanaan | F2: Approve edited and imputed data/Persetujuan hasil validasi, perbaikan, dan imputasi data
C3: Economy-Wide Survey | D3: Economy-Wide Survey | E3: 2100 Biro Perencanaan | F3: Collect Data/Pengumpulan data
C4: Economy-Wide Survey | D4: Economy-Wide Survey | E4: 2100 Biro Perencanaan | F4: Conduct Descriptive Analysis/Melakukan analisis deskriptif
C5: Economy-Wide Survey | D5: Economy-Wide Survey | E5: 2100 Biro Perencanaan | F5: Data Editing and imputation/Perbaikan isian dan imputasi data berdasarkan keadaan lapangan
C6: Economy-Wide Survey | D6: Economy-Wide Survey | E6: 2100 Biro Perencanaan | F6: Data entry/Perekaman Data
C7: Economy-Wide Survey | D7: Economy-Wide Survey | E7: 2100 Biro Perencanaan | F7: Entri dokumen updating/listing
C8: Economy-Wide Survey | D8: Economy-Wide Survey | E8: 2100 Biro Perencanaan | F8: Error report/Konfirmasi hasil validasi data ke petugas
C9: Economy-Wide Survey | D9: Economy-Wide Survey | E9: 2100 Biro Perencanaan | F9: Identifikasi sampel
C10: Economy-Wide Survey | D10: Economy-Wide Survey | E10: 2100 Biro Perencanaan | F10: Input data validation/Melakukan validasi data
C11: Economy-Wide Survey | D11: Economy-Wide Survey | E11: 2100 Biro Perencanaan | F11: Melakukan konsultasi/diskusi dengan peneliti pengguna dan finalisasi temuan dan laporan yang dianalisis/Rekonsiliasi hasil akhir data
C12: Economy-Wide Survey | D12: Economy-Wide Survey | E12: 2100 Biro Perencanaan | F12: Melatih petugas pendataan
C13: Economy-Wide Survey | D13: Economy-Wide Survey | E13: 2100 Biro Perencanaan | F13: Mengarsipkan instrumen pencacahan
... C4957: Implementasi Seea Dalam Sisnerling Indonesia | D4957: Indepth Study Sisnerling | E4957: 7100 Direktorat Neraca Produksi | F4957: Updating/Listing
C4958: Penyusunan Matrik Supply Regional | E4958: 7100 Direktorat Neraca Produksi | F4958: Coding, validasi, dan imputasi data
C4959: Penyusunan Matrik Supply Regional | E4959: 7100 Direktorat Neraca Produksi | F4959: FGD dengan dinas/instansi terkait
C4960: Penyusunan Matrik Supply Regional | E4960: 7100 Direktorat Neraca Produksi | F4960: Melakukan analisis deskriptif
C4961: Penyusunan Matrik Supply Regional | E4961: 7100 Direktorat Neraca Produksi | F4961: Melakukan konsultasi/diskusi dengan peneliti pengguna dan finalisasi temuan dan laporan yang dianalisis/Rekonsiliasi hasil akhir data
C4962: Penyusunan Matrik Supply Regional | E4962: 7100 Direktorat Neraca Produksi | F4962: Mengarsipkan instrumen pengumpulan data
C4963: Penyusunan Matrik Supply Regional | E4963: 7100 Direktorat Neraca Produksi | F4963: Monitor and report data collection progress/Monitoring progress pendataan
C4964: Penyusunan Matrik Supply Regional | E4964: 7100 Direktorat Neraca Produksi | F4964: Non Responds Follow Up/Revisit Non Responds
C4965: Penyusunan Matrik Supply Regional | E4965: 7100 Direktorat Neraca Produksi | F4965: Organize the release/Penyiapan dan melaksanakan rilis data
C4966: Penyusunan Matrik Supply Regional | E4966: 7100 Direktorat Neraca Produksi | F4966: Pelatihan petugas
C4967: Penyusunan Matrik Supply Regional | E4967: 7100 Direktorat Neraca Produksi | F4967: Pengawasan dan pemeriksaan data
C4968: Penyusunan Matrik Supply Regional | E4968: 7100 Direktorat Neraca Produksi | F4968: Pengumpulan data
C4969: Penyusunan Matrik Supply Regional | E4969: 7100 Direktorat Neraca Produksi | F4969: Penyiapan administrasi keuangan
... C4974: Penyusunan Matrik Supply Regional | E4974: 7100 Direktorat Neraca Produksi | F4974: Supervisi pengumpulan data
C4975: Penyusunan Matriks Trade And Transport Margin (TTM) Berbasis SNA 2008 | D4975: Penyusunan Matriks TTM | E4975: 7100 Direktorat Neraca Produksi | F4975: Penyusunan dokumen administrasi
C4976: Penyusunan Matriks Trade And Transport Margin (TTM) Berbasis SNA 2009 | D4976: Penyusunan Matriks TTM | E4976: 7100 Direktorat Neraca Produksi | F4976: Identifikasi sampel
C4977: Penyusunan Matriks Trade And Transport Margin (TTM) Berbasis SNA 2010 | D4977: Penyusunan Matriks TTM | E4977: 7100 Direktorat Neraca Produksi | F4977: Menyusun alokasi petugas lapangan
C4978: Penyusunan Matriks Trade And Transport Margin (TTM) Berbasis SNA 2011 | D4978: Penyusunan Matriks TTM | E4978: 7100 Direktorat Neraca Produksi | F4978: Mengikuti pelatihan instruktur
C4979: Penyusunan Matriks Trade And Transport Margin (TTM) Berbasis SNA 2012 | D4979: Penyusunan Matriks TTM | E4979: 7100 Direktorat Neraca Produksi | F4979: Melatih petugas pendataan
C4980: Penyusunan Matriks Trade And Transport Margin (TTM) Berbasis SNA 2013 | D4980: Penyusunan Matriks TTM | E4980: 7100 Direktorat Neraca Produksi | F4980: Menyiapkan sumber daya dan instrumen pengumpulan data
C4981: Penyusunan Matriks Trade And Transport Margin (TTM) Berbasis SNA 2014 | D4981: Penyusunan Matriks TTM | E4981: 7100 Direktorat Neraca Produksi | F4981: Menyiapkan instrumen untuk quality assurance/penjaminan kualitas
C4982: Penyusunan Matriks Trade And Transport Margin (TTM) Berbasis SNA 2015 | D4982: Penyusunan Matriks TTM | E4982: 7100 Direktorat Neraca Produksi | F4982: Send Out pre-Collection Information/Sosialisasi Kegiatan Survei dan Sensus
C4983: Penyusunan Matriks Trade And Transport Margin (TTM) Berbasis SNA 2016 | D4983: Penyusunan Matriks TTM | E4983: 7100 Direktorat Neraca Produksi | F4983: Updating/Listing
C4984: Penyusunan Matriks Trade And Transport Margin (TTM) Berbasis SNA 2017 | D4984: Penyusunan Matriks TTM | E4984: 7100 Direktorat Neraca Produksi | F4984: Pengawasan/Pemeriksaan dokumen updating/listing
C4985: Penyusunan Matriks Trade And Transport Margin (TTM) Berbasis SNA 2018 | D4985: Penyusunan Matriks TTM | E4985: 7100 Direktorat Neraca Produksi | F4985: Entri dokumen updating/listing
C4986: Penyusunan Matriks Trade And Transport Margin (TTM) Berbasis SNA 2019 | D4986: Penyusunan Matriks TTM | E4986: 7100 Direktorat Neraca Produksi | F4986: Penarikan sampel survei
... C5683: Persiapan Sensus Ekonomi 2026 | D5683: Updating direktori Usaha/Perusahaan Ekonomi | E5683: 9100 Sekretariat SE | F5683: Updating/Listing
